Workbook

Sheet Supuestos
A1: clave | B1: concepto | C1: unidad | D1: común | E1: optimista | F1: neutral | G1: pesimista | H1: fuente
A2: Fuente de cada supuesto: wiki/negocio/analisis-financiero.md. Clave bibliográfica = documento/biblio.bib.
A4: Horizonte, calendario y tasa
A5: horizonte | B5: Horizonte de evaluación | C5: años | D5: 5 | H5: Decisión de #45
A6: anio_0 | B6: Año calendario del año 0 | C6: año | D6: 2026 | H6: Supuesto propio
A7: meses_anio | B7: Meses por año | C7: meses | D7: 12 | H7: —
A8: anio_electoral | B8: Año 0 con elección nacional (1 = sí) | C8: 0/1 | D8: 0 | H8: ConvencionConstituyente1994, LaNacion2026
B9: Año 1 con elección nacional (1 = sí) | C9: 0/1 | D9: 1 | H9: ConvencionConstituyente1994, LaNacion2026
B10: Año 2 con elección nacional (1 = sí) | C10: 0/1 | D10: 0 | H10: ConvencionConstituyente1994, LaNacion2026
B11: Año 3 con elección nacional (1 = sí) | C11: 0/1 | D11: 1 | H11: ConvencionConstituyente1994, LaNacion2026
B12: Año 4 con elección nacional (1 = sí) | C12: 0/1 | D12: 0 | H12: ConvencionConstituyente1994, LaNacion2026
B13: Año 5 con elección nacional (1 = sí) | C13: 0/1 | D13: 1 | H13: ConvencionConstituyente1994, LaNacion2026
A14: tasa_libre_riesgo | B14: Bono del Tesoro de EE. UU. a 10 años | C14: % | D14: 0.0517 | H14: FederalReserve2026
A15: riesgo_pais | B15: Riesgo país de Argentina (EMBI, 628 pb) | C15: % | D15: 0.0628 | H15: Infobae2026
A16: prima_proyecto | B16: Prima por proyecto nuevo | C16: % | D16: 0.1355 | H16: Supuesto propio, Damodaran2010
A17: tasa_descuento | B17: Tasa de descuento | C17: % | D17: =tasa_libre_riesgo+riesgo_pais+prima_proyecto -> 0.25 | H17: Suma de componentes
A18: erp_maduro | B18: Prima de riesgo de un mercado maduro (contraste CAPM) | C18: % | D18: 0.0423 | H18: Damodaran2026
A19: crp_argentina | B19: Prima de riesgo país de Argentina (contraste CAPM) | C19: % | D19: 0.0971 | H19: Damodaran2026
A20: tasa_capm | B20: Tasa CAPM de contraste, con beta igual a 1 | C20: % | D20: =tasa_libre_riesgo+erp_maduro+crp_argentina -> 0.1911 | H20: Cálculo
A21: crecimiento_perpetuo | B21: Crecimiento a perpetuidad para el valor residual | C21: % | D21: 0.02 | H21: Supuesto propio, no mayor al crecimiento de largo plazo
A23: Recursos humanos
A24: sueldo_ars | B24: Sueldo bruto mensual, developer semi senior | C24: ARS/mes | D24: 2501629 | H24: Sysarmy2026
A25: tc_encuesta | B25: Tipo de cambio implícito de la encuesta | C25: ARS/USD | D25: 1397.88 | H25: Sysarmy2026
A26: sueldo_usd | B26: Sueldo bruto mensual en USD | C26: USD/mes | D26: =ROUND(sueldo_ars/tc_encuesta,0) -> 1790 | H26: Cálculo
A27: sueldos_por_anio | B27: Sueldos por año (12 + aguinaldo) | C27: sueldos | D27: 13 | H27: Supuesto propio
A28: ajuste_sueldo | B28: Ajuste anual del sueldo en USD | C28: % | D28: 0.05 | H28: Supuesto propio
A29: cargas_sociales | B29: Cargas sociales del empleador (18 % + obra social 6 % + ART 2 %) | C29: % | D29: 0.26 | H29: CongresoNacion2019; ART: supuesto propio
A30: meses_anio_0 | B30: Meses de desarrollo del trabajo en el año 0 (no se imputan al flujo) | C30: meses | D30: 10 | H30: Cronograma del PFI
A32: Impuestos y capital de trabajo
A33: alicuota_ganancias | B33: Impuesto a las ganancias, con quebrantos trasladables | C33: % | D33: 0.35 | H33: Simplificación indicada por la cátedra
A34: meses_cobro | B34: Plazo de cobro de los clientes B2B y B2G | C34: meses | D34: 2 | H34: Supuesto propio
A36: Inversión del año 0 (además del desarrollo)
A37: inv_infraestructura_0 | B37: Infraestructura durante el PFI: API y clasificador en Railway (13 USD/mes × 12) | C37: USD | D37: 156 | H37: Cap. 4, RNF-14; RailwayPrecios2026
A38: inv_dominio | B38: Dominio .com.ar, primer año (ARS 8.500) | C38: USD | D38: 5.5 | H38: NICArgentina2026
A39: inv_marca_inpi | B39: Solicitud de marca en el INPI, clases 9 y 42 (200 UMAPI) | C39: USD | D39: 53 | H39: INPI2026, INPIUmapi2026
A40: inv_legal | B40: Asesoría legal | C40: USD | D40: 1500 | H40: Supuesto propio
A42: Infraestructura y hosting (años 1 a 5)
A43: infra_base | B43: Base comercial: Railway Pro, con 20 USD de uso incluidos (API y clasificador, 13 USD/mes) | C43: USD/mes | D43: 20 | H43: Railway2026
A44: infra_escalado | B44: Uso adicional por cada bloque de usuarios activos (1 GB de memoria) | C44: USD/mes | D44: 10 | H44: Supuesto propio; tarifa RailwayPrecios2026
A45: ua_escalado | B45: Usuarios activos por bloque de escalado | C45: UA | D45: 10000 | H45: Supuesto propio
A46: dominio_anual | B46: Renovación del dominio .com.ar (ARS 8.500) | C46: USD/año | D46: 5.5 | H46: NICArgentina2026
A47: marketing | B47: Marketing, año 1 | C47: USD/año | E47: 6000 | F47: 4000 | G47: 2000 | H47: Supuesto propio
B48: Marketing, año 2 | C48: USD/año | E48: 9000 | F48: 6000 | G48: 3000 | H48: Supuesto propio
B49: Marketing, año 3 | C49: USD/año | E49: 12000 | F49: 8000 | G49: 4000 | H49: Supuesto propio
B50: Marketing, año 4 | C50: USD/año | E50: 15000 | F50: 10000 | G50: 5000 | H50: Supuesto propio
B51: Marketing, año 5 | C51: USD/año | E51: 18000 | F51: 12000 | G51: 6000 | H51: Supuesto propio
A53: Costo variable por análisis
A54: precio_entrada | B54: gpt-5.6-luna, entrada | C54: USD/1 M tokens | D54: 0.2 | H54: OpenAI2026
A55: precio_salida | B55: gpt-5.6-luna, salida | C55: USD/1 M tokens | D55: 1.2 | H55: OpenAI2026
A56: precio_busqueda | B56: Herramienta web_search | C56: USD/llamada | D56: 0.01 | H56: OpenAI2026
A57: tokens_por_millon | B57: Tokens por millón | C57: tokens | D57: 1000000 | H57: —
A58: tokens_entrada | B58: Tokens de entrada por análisis | C58: tokens | E58: 6220 | F58: 11220 | G58: 18220 | H58: Supuesto propio; contraste: Cap. 4, RNF-14
A59: tokens_salida | B59: Tokens de salida por análisis | C59: tokens | E59: 1250 | F59: 2000 | G59: 3600 | H59: Supuesto propio; contraste: Cap. 4, RNF-14
A60: busquedas | B60: Llamadas a web_search por análisis | C60: llamadas | E60: 1 | F60: 2 | G60: 3 | H60: Supuesto propio
A61: costo_analisis | B61: Costo por análisis | C61: USD | E61: =(E58*precio_entrada+E59*precio_salida)/tokens_por_millon+E60*precio_busqueda -> 0.012744 | F61: =(F58*precio_entrada+F59*precio_salida)/tokens_por_millon+F60*precio_busqueda -> 0.024644 | G61: =(G58*precio_entrada+G59*precio_salida)/tokens_por_millon+G60*precio_busqueda -> 0.037964 | H61: Cálculo
A62: usuarios_activos | B62: Usuarios activos mensuales, año 1 | C62: UA | E62: 5000 | F62: 2000 | G62: 500 | H62: Supuesto propio
B63: Usuarios activos mensuales, año 2 | C63: UA | E63: 20000 | F63: 8000 | G63: 2000 | H63: Supuesto propio
B64: Usuarios activos mensuales, año 3 | C64: UA | E64: 50000 | F64: 20000 | G64: 5000 | H64: Supuesto propio
B65: Usuarios activos mensuales, año 4 | C65: UA | E65: 100000 | F65: 40000 | G65: 8000 | H65: Supuesto propio
B66: Usuarios activos mensuales, año 5 | C66: UA | E66: 150000 | F66: 60000 | G66: 10000 | H66: Supuesto propio
A67: analisis_por_ua_mes | B67: Análisis por usuario activo por mes | C67: análisis | E67: 20 | F67: 12 | G67: 6 | H67: Supuesto propio
A68: tope_mensual | B68: Tope de análisis a demanda nuevos por instalación por mes | C68: análisis | D68: 5 | H68: Decisión de producto (RF-17)
A69: tasa_reuso | B69: Análisis servidos desde la caché (las publicaciones virales concentran la demanda) | C69: % | E69: 0.4 | F69: 0.3 | G69: 0.2 | H69: Supuesto propio
A70: consultas_pro_mes | B70: Demanda de consultas por cliente de la API intermedia por mes (se costea hasta la cuota) | C70: consultas | E70: 2000 | F70: 4000 | G70: 8000 | H70: Supuesto propio
A71: consultas_ent_mes | B71: Demanda de consultas por cliente de la API superior por mes (se costea hasta la cuota) | C71: consultas | E71: 20000 | F71: 40000 | G71: 80000 | H71: Supuesto propio
A72: cuota_intermedia | B72: Cuota mensual incluida en la API intermedia | C72: consultas | D72: 5000 | H72: Cap. 3, tab:pricing
A73: cuota_superior | B73: Cuota mensual incluida en la API superior | C73: consultas | D73: 40000 | H73: Cap. 3, tab:pricing
A74: precio_excedente | B74: Precio por consulta excedente sobre la cuota (no se modela) | C74: USD/consulta | D74: 0.04 | H74: Cap. 3, tab:pricing
A76: Clientes B2B
A77: u_medios_total | B77: Universo: socios activos de ADEPA, con y sin sitio web | C77: organizaciones | D77: 130 | H77: ADEPA2026
A78: u_medios_grandes | B78: Universo: medios de gran porte | C78: organizaciones | D78: 10 | H78: ADEPA2026 (corte propio)
A79: u_medios_chicos | B79: Universo: resto de medios de ADEPA con sitio web | C79: organizaciones | D79: 93 | H79: ADEPA2026
A80: u_verificadores | B80: Universo: verificadores | C80: organizaciones | D80: 3 | H80: LatamChequea2026
A81: u_universidades | B81: Universo: universidades | C81: organizaciones | D81: 149 | H81: SubsecretariaPoliticasUniversitarias2026
A82: u_organismos | B82: Universo: organismos electorales y ONG | C82: organizaciones | D82: 32 | H82: MinisterioInterior2026
A83: u_agencias | B83: Universo: agencias | C83: organizaciones | D83: 120 | H83: AgenciasArgentinas2026
A84: precio_medios_grandes | B84: Precio: API nivel superior, medios de gran porte | C84: USD/mes | E84: 3000 | F84: 2500 | G84: 1500 | H84: Cap. 3, tab:pricing
A85: precio_medios_chicos | B85: Precio: API nivel intermedio | C85: USD/mes | D85: 200 | H85: Cap. 3, tab:pricing
A86: precio_verificadores | B86: Precio: panel de tendencias + API intermedia | C86: USD/mes | D86: 500 | H86: Cap. 3, tab:pricing
A87: precio_universidades | B87: Precio: acceso histórico | C87: USD/mes | D87: 100 | H87: Cap. 3, tab:pricing
A88: precio_organismos | B88: Precio: reporte de monitoreo electoral | C88: USD/contrato | E88: 30000 | F88: 20000 | G88: 10000 | H88: Cap. 3, tab:pricing
A89: precio_agencias | B89: Precio: API nivel superior, agencias | C89: USD/mes | E89: 3000 | F89: 2500 | G89: 1500 | H89: Cap. 3, tab:pricing
A90: ua_inicio_b2b | B90: Usuarios activos mensuales desde los que empiezan las ventas B2B | C90: UA | D90: 5000 | H90: Supuesto propio
A91: capt_medios_grandes | B91: Captación anual: medios de gran porte | C91: % | E91: 0.2 | F91: 0.1 | G91: 0.05 | H91: Supuesto propio
A92: capt_medios_chicos | B92: Captación anual: resto de medios de ADEPA | C92: % | E92: 0.1 | F92: 0.05 | G92: 0.02 | H92: Supuesto propio
A93: capt_verificadores | B93: Captación anual: verificadores | C93: % | E93: 0.4 | F93: 0.3 | G93: 0.2 | H93: Supuesto propio
A94: capt_universidades | B94: Captación anual: universidades | C94: % | E94: 0.08 | F94: 0.04 | G94: 0.02 | H94: Supuesto propio
A95: capt_organismos | B95: Fracción de organismos que contrata en año electoral | C95: % | E95: 0.1 | F95: 0.06 | G95: 0.03 | H95: Supuesto propio
A96: capt_agencias | B96: Captación anual: agencias | C96: % | E96: 0.05 | F96: 0.02 | G96: 0.01 | H96: Supuesto propio
A97: churn_medios_grandes | B97: Churn anual: medios de gran porte | C97: % | E97: 0.1 | F97: 0.15 | G97: 0.25 | H97: Supuesto propio
A98: churn_medios_chicos | B98: Churn anual: resto de medios de ADEPA | C98: % | E98: 0.15 | F98: 0.2 | G98: 0.3 | H98: Supuesto propio
A99: churn_verificadores | B99: Churn anual: verificadores | C99: % | E99: 0 | F99: 0.1 | G99: 0.2 | H99: Supuesto propio
A100: churn_universidades | B100: Churn anual: universidades | C100: % | E100: 0.05 | F100: 0.1 | G100: 0.15 | H100: Supuesto propio
A101: churn_agencias | B101: Churn anual: agencias | C101: % | E101: 0.15 | F101: 0.2 | G101: 0.3 | H101: Supuesto propio
A103: Sensibilidad (1 = caso base; los cambia scripts/sensibilidad_modelo_financiero.py)
A104: sens_costo_analisis | B104: Multiplicador del costo por análisis | C104: veces | D104: 1 | H104: —
A105: sens_precios | B105: Multiplicador de los precios B2B | C105: veces | D105: 1 | H105: —
A106: sens_captacion | B106: Multiplicador de las tasas de captación | C106: veces | D106: 1 | H106: —

Sheet Resumen
A1: Indicador | B1: Optimista | C1: Neutral | D1: Pesimista
A2: VAN (USD) | B2: =Optimista!B74 -> 833353.48 | C2: =Neutral!B74 -> 63935.762 | D2: =Pesimista!B74 -> -94161.066
A3: TIR | B3: =Optimista!B75 -> 55.545393 | C3: =Neutral!B75 -> 0.72550446 | D3: =Pesimista!B75 -> no definida
A4: Payback simple (años) | B4: =Optimista!B76 -> 0.018458976 | C4: =Neutral!B76 -> 2.9321736 | D4: =Pesimista!B76 -> no se recupera
A5: Payback descontado (años) | B5: =Optimista!B77 -> 0.02307372 | C5: =Neutral!B77 -> 3.4622135 | D5: =Pesimista!B77 -> no se recupera
A6: Punto de equilibrio (clientes B2B) | B6: =Optimista!B80 -> 17 | C6: =Neutral!B80 -> 23 | D6: =Pesimista!B80 -> 21
A7: Ingreso medio por cliente B2B en el año 5 (USD) | B7: =Optimista!B79 -> 10781.443 | C7: =Neutral!B79 -> 8901.2048 | D7: =Pesimista!B79 -> 5600
A8: VAN con valor residual (USD) | B8: =Optimista!B78 -> 1609256.9 | C8: =Neutral!B78 -> 199501.17 | D8: =Pesimista!B78 -> -94161.066
A10: Mercado, a precios del escenario neutral (USD por año)
A11: TAM: todo el universo de organizaciones contrata | B11: =meses_anio*(u_medios_grandes*INDEX(precio_medios_grandes,1,2)+(u_medios_total-u_medios_grandes)*precio_medios_chicos+u_verificadores*precio_verificadores+u_universidades*precio_universidades+u_agencias*INDEX(precio_agencias,1,2))+u_organismos*INDEX(precio_organismos,1,2) -> 5024800
A12: SAM: organizaciones que el producto y el canal atienden | B12: =meses_anio*(u_medios_grandes*INDEX(precio_medios_grandes,1,2)+u_medios_chicos*precio_medios_chicos+u_verificadores*precio_verificadores+u_universidades*precio_universidades+u_agencias*INDEX(precio_agencias,1,2))+u_organismos*INDEX(precio_organismos,1,2) -> 4960000
A13: SOM: ingresos del año 5, escenario neutral | B13: =Neutral!G45 -> 369400
A15: Contraste para la defensa
A16: Valor de mercado de las horas de desarrollo del año 0, no imputado (USD) | B16: =meses_anio_0*sueldo_usd*(1+cargas_sociales)*sueldos_por_anio/meses_anio -> 24433.5
A17: Tasa CAPM de contraste | B17: =tasa_capm -> 0.1911
A19: Margen mensual por cliente a cuota llena (USD) | B19: Optimista | C19: Neutral | D19: Pesimista
A20: API intermedia: costo variable a cuota llena | B20: =cuota_intermedia*(1-INDEX(tasa_reuso,1,1))*INDEX(costo_analisis,1,1)*sens_costo_analisis -> 38.232 | C20: =cuota_intermedia*(1-INDEX(tasa_reuso,1,2))*INDEX(costo_analisis,1,2)*sens_costo_analisis -> 86.254 | D20: =cuota_intermedia*(1-INDEX(tasa_reuso,1,3))*INDEX(costo_analisis,1,3)*sens_costo_analisis -> 151.856
A21: API intermedia: margen a cuota llena | B21: =precio_medios_chicos*sens_precios-cuota_intermedia*(1-INDEX(tasa_reuso,1,1))*INDEX(costo_analisis,1,1)*sens_costo_analisis -> 161.768 | C21: =precio_medios_chicos*sens_precios-cuota_intermedia*(1-INDEX(tasa_reuso,1,2))*INDEX(costo_analisis,1,2)*sens_costo_analisis -> 113.746 | D21: =precio_medios_chicos*sens_precios-cuota_intermedia*(1-INDEX(tasa_reuso,1,3))*INDEX(costo_analisis,1,3)*sens_costo_analisis -> 48.144
A22: API superior: costo variable a cuota llena | B22: =cuota_superior*(1-INDEX(tasa_reuso,1,1))*INDEX(costo_analisis,1,1)*sens_costo_analisis -> 305.856 | C22: =cuota_superior*(1-INDEX(tasa_reuso,1,2))*INDEX(costo_analisis,1,2)*sens_costo_analisis -> 690.032 | D22: =cuota_superior*(1-INDEX(tasa_reuso,1,3))*INDEX(costo_analisis,1,3)*sens_costo_analisis -> 1214.848
A23: API superior: margen a cuota llena | B23: =INDEX(precio_medios_grandes,1,1)*sens_precios-cuota_superior*(1-INDEX(tasa_reuso,1,1))*INDEX(costo_analisis,1,1)*sens_costo_analisis -> 2694.144 | C23: =INDEX(precio_medios_grandes,1,2)*sens_precios-cuota_superior*(1-INDEX(tasa_reuso,1,2))*INDEX(costo_analisis,1,2)*sens_costo_analisis -> 1809.968 | D23: =INDEX(precio_medios_grandes,1,3)*sens_precios-cuota_superior*(1-INDEX(tasa_reuso,1,3))*INDEX(costo_analisis,1,3)*sens_costo_analisis -> 285.152
A25: Economía unitaria, escenario neutral (USD) | B25: Precio mensual | C25: Costo variable mensual | D25: Margen mensual | E25: Churn anual | F25: LTV | G25: LTV/CAC | H25: Payback del CAC (meses)
A26: CAC (USD por alta de suscripción) | B26: =SUM(Neutral!C50:G50)/(SUM(Neutral!C12:G12)+SUM(Neutral!C17:G17)+SUM(Neutral!C22:G22)+SUM(Neutral!C27:G27)+SUM(Neutral!C32:G32)) -> 740.74074
A27: Unitaria: Medios de gran porte | B27: =INDEX(precio_medios_grandes,1,2)*sens_precios -> 2500 | C27: =MIN(INDEX(consultas_ent_mes,1,2),cuota_superior)*(1-INDEX(tasa_reuso,1,2))*INDEX(costo_analisis,1,2)*sens_costo_analisis -> 690.032 | D27: =B27-C27 -> 1809.968 | E27: =INDEX(churn_medios_grandes,1,2) -> 0.15 | F27: =D27*meses_anio/E27 -> 144797.44 | G27: =F27/$B$26 -> 195.47654 | H27: =$B$26/D27 -> 0.40925626
A28: Unitaria: Medios socios de ADEPA (resto) | B28: =precio_medios_chicos*sens_precios -> 200 | C28: =MIN(INDEX(consultas_pro_mes,1,2),cuota_intermedia)*(1-INDEX(tasa_reuso,1,2))*INDEX(costo_analisis,1,2)*sens_costo_analisis -> 69.0032 | D28: =B28-C28 -> 130.9968 | E28: =INDEX(churn_medios_chicos,1,2) -> 0.2 | F28: =D28*meses_anio/E28 -> 7859.808 | G28: =F28/$B$26 -> 10.610741 | H28: =$B$26/D28 -> 5.6546476
A29: Unitaria: Verificadores | B29: =precio_verificadores*sens_precios -> 500 | C29: =MIN(INDEX(consultas_pro_mes,1,2),cuota_intermedia)*(1-INDEX(tasa_reuso,1,2))*INDEX(costo_analisis,1,2)*sens_costo_analisis -> 69.0032 | D29: =B29-C29 -> 430.9968 | E29: =INDEX(churn_verificadores,1,2) -> 0.1 | F29: =D29*meses_anio/E29 -> 51719.616 | G29: =F29/$B$26 -> 69.821482 | H29: =$B$26/D29 -> 1.7186688
A30: Unitaria: Universidades y observatorios | B30: =precio_universidades*sens_precios -> 100 | C30: =0*(1-INDEX(tasa_reuso,1,2))*INDEX(costo_analisis,1,2)*sens_costo_analisis -> 0 | D30: =B30-C30 -> 100 | E30: =INDEX(churn_universidades,1,2) -> 0.1 | F30: =D30*meses_anio/E30 -> 12000 | G30: =F30/$B$26 -> 16.2 | H30: =$B$26/D30 -> 7.4074074
A31: Unitaria: Agencias | B31: =INDEX(precio_agencias,1,2)*sens_precios -> 2500 | C31: =MIN(INDEX(consultas_ent_mes,1,2),cuota_superior)*(1-INDEX(tasa_reuso,1,2))*INDEX(costo_analisis,1,2)*sens_costo_analisis -> 690.032 | D31: =B31-C31 -> 1809.968 | E31: =INDEX(churn_agencias,1,2) -> 0.2 | F31: =D31*meses_anio/E31 -> 108598.08 | G31: =F31/$B$26 -> 146.60741 | H31: =$B$26/D31 -> 0.40925626

Sheet Optimista
A1: Escenario optimista (USD nominales; todo lo derivado es fórmula)
A2: Columna de escenario en Supuestos (1 = optimista, 2 = neutral, 3 = pesimista) | B2: 1
A3: Año | B3: =COLUMN()-2 -> 0 | C3: =COLUMN()-2 -> 1 | D3: =COLUMN()-2 -> 2 | E3: =COLUMN()-2 -> 3 | F3: =COLUMN()-2 -> 4 | G3: =COLUMN()-2 -> 5
A4: Año calendario | B4: =anio_0+B$3 -> 2026 | C4: =anio_0+C$3 -> 2027 | D4: =anio_0+D$3 -> 2028 | E4: =anio_0+E$3 -> 2029 | F4: =anio_0+F$3 -> 2030 | G4: =anio_0+G$3 -> 2031
A5: Año electoral (1 = sí) | B5: =INDEX(anio_electoral,B$3+1) -> 0 | C5: =INDEX(anio_electoral,C$3+1) -> 1 | D5: =INDEX(anio_electoral,D$3+1) -> 0 | E5: =INDEX(anio_electoral,E$3+1) -> 1 | F5: =INDEX(anio_electoral,F$3+1) -> 0 | G5: =INDEX(anio_electoral,G$3+1) -> 1
A6: Usuarios activos mensuales | C6: =INDEX(usuarios_activos,C$3,$B$2) -> 5000 | D6: =INDEX(usuarios_activos,D$3,$B$2) -> 20000 | E6: =INDEX(usuarios_activos,E$3,$B$2) -> 50000 | F6: =INDEX(usuarios_activos,F$3,$B$2) -> 100000 | G6: =INDEX(usuarios_activos,G$3,$B$2) -> 150000
A7: Ventas B2B habilitadas (1 = sí) | C7: =IF(C6>=ua_inicio_b2b,1,0) -> 1 | D7: =IF(D6>=ua_inicio_b2b,1,0) -> 1 | E7: =IF(E6>=ua_inicio_b2b,1,0) -> 1 | F7: =IF(F6>=ua_inicio_b2b,1,0) -> 1 | G7: =IF(G6>=ua_inicio_b2b,1,0) -> 1
A9: Clientes B2B
A10: Medios de gran porte: activos al inicio | C10: =N(B13) -> 0 | D10: =N(C13) -> 2 | E10: =N(D13) -> 4 | F10: =N(E13) -> 5 | G10: =N(F13) -> 5
A11: Medios de gran porte: bajas | C11: =ROUND(INDEX(churn_medios_grandes,1,$B$2)*C10,0) -> 0 | D11: =ROUND(INDEX(churn_medios_grandes,1,$B$2)*D10,0) -> 0 | E11: =ROUND(INDEX(churn_medios_grandes,1,$B$2)*E10,0) -> 0 | F11: =ROUND(INDEX(churn_medios_grandes,1,$B$2)*F10,0) -> 1 | G11: =ROUND(INDEX(churn_medios_grandes,1,$B$2)*G10,0) -> 1
A12: Medios de gran porte: altas | C12: =C7*ROUND(INDEX(capt_medios_grandes,1,$B$2)*sens_captacion*(u_medios_grandes-C10),0) -> 2 | D12: =D7*ROUND(INDEX(capt_medios_grandes,1,$B$2)*sens_captacion*(u_medios_grandes-D10),0) -> 2 | E12: =E7*ROUND(INDEX(capt_medios_grandes,1,$B$2)*sens_captacion*(u_medios_grandes-E10),0) -> 1 | F12: =F7*ROUND(INDEX(capt_medios_grandes,1,$B$2)*sens_captacion*(u_medios_grandes-F10),0) -> 1 | G12: =G7*ROUND(INDEX(capt_medios_grandes,1,$B$2)*sens_captacion*(u_medios_grandes-G10),0) -> 1
A13: Medios de gran porte: activos al cierre | C13: =C10+C12-C11 -> 2 | D13: =D10+D12-D11 -> 4 | E13: =E10+E12-E11 -> 5 | F13: =F10+F12-F11 -> 5 | G13: =G10+G12-G11 -> 5
A14: Medios de gran porte: promedio del año | C14: =(C10+C13)/2 -> 1 | D14: =(D10+D13)/2 -> 3 | E14: =(E10+E13)/2 -> 4.5 | F14: =(F10+F13)/2 -> 5 | G14: =(G10+G13)/2 -> 5
A15: Medios socios de ADEPA (resto): activos al inicio | C15: =N(B18) -> 0 | D15: =N(C18) -> 9 | E15: =N(D18) -> 16 | F15: =N(E18) -> 22 | G15: =N(F18) -> 26
A16: Medios socios de ADEPA (resto): bajas | C16: =ROUND(INDEX(churn_medios_chicos,1,$B$2)*C15,0) -> 0 | D16: =ROUND(INDEX(churn_medios_chicos,1,$B$2)*D15,0) -> 1 | E16: =ROUND(INDEX(churn_medios_chicos,1,$B$2)*E15,0) -> 2 | F16: =ROUND(INDEX(churn_medios_chicos,1,$B$2)*F15,0) -> 3 | G16: =ROUND(INDEX(churn_medios_chicos,1,$B$2)*G15,0) -> 4
A17: Medios socios de ADEPA (resto): altas | C17: =C7*ROUND(INDEX(capt_medios_chicos,1,$B$2)*sens_captacion*(u_medios_chicos-C15),0) -> 9 | D17: =D7*ROUND(INDEX(capt_medios_chicos,1,$B$2)*sens_captacion*(u_medios_chicos-D15),0) -> 8 | E17: =E7*ROUND(INDEX(capt_medios_chicos,1,$B$2)*sens_captacion*(u_medios_chicos-E15),0) -> 8 | F17: =F7*ROUND(INDEX(capt_medios_chicos,1,$B$2)*sens_captacion*(u_medios_chicos-F15),0) -> 7 | G17: =G7*ROUND(INDEX(capt_medios_chicos,1,$B$2)*sens_captacion*(u_medios_chicos-G15),0) -> 7
A18: Medios socios de ADEPA (resto): activos al cierre | C18: =C15+C17-C16 -> 9 | D18: =D15+D17-D16 -> 16 | E18: =E15+E17-E16 -> 22 | F18: =F15+F17-F16 -> 26 | G18: =G15+G17-G16 -> 29
A19: Medios socios de ADEPA (resto): promedio del año | C19: =(C15+C18)/2 -> 4.5 | D19: =(D15+D18)/2 -> 12.5 | E19: =(E15+E18)/2 -> 19 | F19: =(F15+F18)/2 -> 24 | G19: =(G15+G18)/2 -> 27.5
A20: Verificadores: activos al inicio | C20: =N(B23) -> 0 | D20: =N(C23) -> 1 | E20: =N(D23) -> 2 | F20: =N(E23) -> 2 | G20: =N(F23) -> 2
A21: Verificadores: bajas | C21: =ROUND(INDEX(churn_verificadores,1,$B$2)*C20,0) -> 0 | D21: =ROUND(INDEX(churn_verificadores,1,$B$2)*D20,0) -> 0 | E21: =ROUND(INDEX(churn_verificadores,1,$B$2)*E20,0) -> 0 | F21: =ROUND(INDEX(churn_verificadores,1,$B$2)*F20,0) -> 0 | G21: =ROUND(INDEX(churn_verificadores,1,$B$2)*G20,0) -> 0
A22: Verificadores: altas | C22: =C7*ROUND(INDEX(capt_verificadores,1,$B$2)*sens_captacion*(u_verificadores-C20),0) -> 1 | D22: =D7*ROUND(INDEX(capt_verificadores,1,$B$2)*sens_captacion*(u_verificadores-D20),0) -> 1 | E22: =E7*ROUND(INDEX(capt_verificadores,1,$B$2)*sens_captacion*(u_verificadores-E20),0) -> 0 | F22: =F7*ROUND(INDEX(capt_verificadores,1,$B$2)*sens_captacion*(u_verificadores-F20),0) -> 0 | G22: =G7*ROUND(INDEX(capt_verificadores,1,$B$2)*sens_captacion*(u_verificadores-G20),0) -> 0
A23: Verificadores: activos al cierre | C23: =C20+C22-C21 -> 1 | D23: =D20+D22-D21 -> 2 | E23: =E20+E22-E21 -> 2 | F23: =F20+F22-F21 -> 2 | G23: =G20+G22-G21 -> 2
A24: Verificadores: promedio del año | C24: =(C20+C23)/2 -> 0.5 | D24: =(D20+D23)/2 -> 1.5 | E24: =(E20+E23)/2 -> 2 | F24: =(F20+F23)/2 -> 2 | G24: =(G20+G23)/2 -> 2
A25: Universidades y observatorios: activos al inicio | C25: =N(B28) -> 0 | D25: =N(C28) -> 12 | E25: =N(D28) -> 22 | F25: =N(E28) -> 31 | G25: =N(F28) -> 38
A26: Universidades y observatorios: bajas | C26: =ROUND(INDEX(churn_universidades,1,$B$2)*C25,0) -> 0 | D26: =ROUND(INDEX(churn_universidades,1,$B$2)*D25,0) -> 1 | E26: =ROUND(INDEX(churn_universidades,1,$B$2)*E25,0) -> 1 | F26: =ROUND(INDEX(churn_universidades,1,$B$2)*F25,0) -> 2 | G26: =ROUND(INDEX(churn_universidades,1,$B$2)*G25,0) -> 2
A27: Universidades y observatorios: altas | C27: =C7*ROUND(INDEX(capt_universidades,1,$B$2)*sens_captacion*(u_universidades-C25),0) -> 12 | D27: =D7*ROUND(INDEX(capt_universidades,1,$B$2)*sens_captacion*(u_universidades-D25),0) -> 11 | E27: =E7*ROUND(INDEX(capt_universidades,1,$B$2)*sens_captacion*(u_universidades-E25),0) -> 10 | F27: =F7*ROUND(INDEX(capt_universidades,1,$B$2)*sens_captacion*(u_universidades-F25),0) -> 9 | G27: =G7*ROUND(INDEX(capt_universidades,1,$B$2)*sens_captacion*(u_universidades-G25),0) -> 9
A28: Universidades y observatorios: activos al cierre | C28: =C25+C27-C26 -> 12 | D28: =D25+D27-D26 -> 22 | E28: =E25+E27-E26 -> 31 | F28: =F25+F27-F26 -> 38 | G28: =G25+G27-G26 -> 45
A29: Universidades y observatorios: promedio del año | C29: =(C25+C28)/2 -> 6 | D29: =(D25+D28)/2 -> 17 | E29: =(E25+E28)/2 -> 26.5 | F29: =(F25+F28)/2 -> 34.5 | G29: =(G25+G28)/2 -> 41.5
A30: Agencias: activos al inicio | C30: =N(B33) -> 0 | D30: =N(C33) -> 6 | E30: =N(D33) -> 11 | F30: =N(E33) -> 14 | G30: =N(F33) -> 17
A31: Agencias: bajas | C31: =ROUND(INDEX(churn_agencias,1,$B$2)*C30,0) -> 0 | D31: =ROUND(INDEX(churn_agencias,1,$B$2)*D30,0) -> 1 | E31: =ROUND(INDEX(churn_agencias,1,$B$2)*E30,0) -> 2 | F31: =ROUND(INDEX(churn_agencias,1,$B$2)*F30,0) -> 2 | G31: =ROUND(INDEX(churn_agencias,1,$B$2)*G30,0) -> 3
A32: Agencias: altas | C32: =C7*ROUND(INDEX(capt_agencias,1,$B$2)*sens_captacion*(u_agencias-C30),0) -> 6 | D32: =D7*ROUND(INDEX(capt_agencias,1,$B$2)*sens_captacion*(u_agencias-D30),0) -> 6 | E32: =E7*ROUND(INDEX(capt_agencias,1,$B$2)*sens_captacion*(u_agencias-E30),0) -> 5 | F32: =F7*ROUND(INDEX(capt_agencias,1,$B$2)*sens_captacion*(u_agencias-F30),0) -> 5 | G32: =G7*ROUND(INDEX(capt_agencias,1,$B$2)*sens_captacion*(u_agencias-G30),0) -> 5
A33: Agencias: activos al cierre | C33: =C30+C32-C31 -> 6 | D33: =D30+D32-D31 -> 11 | E33: =E30+E32-E31 -> 14 | F33: =F30+F32-F31 -> 17 | G33: =G30+G32-G31 -> 19
A34: Agencias: promedio del año | C34: =(C30+C33)/2 -> 3 | D34: =(D30+D33)/2 -> 8.5 | E34: =(E30+E33)/2 -> 12.5 | F34: =(F30+F33)/2 -> 15.5 | G34: =(G30+G33)/2 -> 18
A35: Organismos y ONG: contratos | C35: =C5*C7*ROUND(INDEX(capt_organismos,1,$B$2)*sens_captacion*u_organismos,0) -> 3 | D35: =D5*D7*ROUND(INDEX(capt_organismos,1,$B$2)*sens_captacion*u_organismos,0) -> 0 | E35: =E5*E7*ROUND(INDEX(capt_organismos,1,$B$2)*sens_captacion*u_organismos,0) -> 3 | F35: =F5*F7*ROUND(INDEX(capt_organismos,1,$B$2)*sens_captacion*u_organismos,0) -> 0 | G35: =G5*G7*ROUND(INDEX(capt_organismos,1,$B$2)*sens_captacion*u_organismos,0) -> 3
A36: Clientes B2B (promedio del año, con contratos) | C36: =C14+C19+C24+C29+C34+C35 -> 18 | D36: =D14+D19+D24+D29+D34+D35 -> 42.5 | E36: =E14+E19+E24+E29+E34+E35 -> 67.5 | F36: =F14+F19+F24+F29+F34+F35 -> 81 | G36: =G14+G19+G24+G29+G34+G35 -> 97
A38: Ingresos por producto
A39: Ingresos: API nivel superior (Medios de gran porte) | C39: =C14*INDEX(precio_medios_grandes,1,$B$2)*sens_precios*meses_anio -> 36000 | D39: =D14*INDEX(precio_medios_grandes,1,$B$2)*sens_precios*meses_anio -> 108000 | E39: =E14*INDEX(precio_medios_grandes,1,$B$2)*sens_precios*meses_anio -> 162000 | F39: =F14*INDEX(precio_medios_grandes,1,$B$2)*sens_precios*meses_anio -> 180000 | G39: =G14*INDEX(precio_medios_grandes,1,$B$2)*sens_precios*meses_anio -> 180000
A40: Ingresos: API nivel intermedio (Medios socios de ADEPA (resto)) | C40: =C19*precio_medios_chicos*sens_precios*meses_anio -> 10800 | D40: =D19*precio_medios_chicos*sens_precios*meses_anio -> 30000 | E40: =E19*precio_medios_chicos*sens_precios*meses_anio -> 45600 | F40: =F19*precio_medios_chicos*sens_precios*meses_anio -> 57600 | G40: =G19*precio_medios_chicos*sens_precios*meses_anio -> 66000
A41: Ingresos: panel de tendencias y API intermedia (Verificadores) | C41: =C24*precio_verificadores*sens_precios*meses_anio -> 3000 | D41: =D24*precio_verificadores*sens_precios*meses_anio -> 9000 | E41: =E24*precio_verificadores*sens_precios*meses_anio -> 12000 | F41: =F24*precio_verificadores*sens_precios*meses_anio -> 12000 | G41: =G24*precio_verificadores*sens_precios*meses_anio -> 12000
A42: Ingresos: acceso histórico (Universidades y observatorios) | C42: =C29*precio_universidades*sens_precios*meses_anio -> 7200 | D42: =D29*precio_universidades*sens_precios*meses_anio -> 20400 | E42: =E29*precio_universidades*sens_precios*meses_anio -> 31800 | F42: =F29*precio_universidades*sens_precios*meses_anio -> 41400 | G42: =G29*precio_universidades*sens_precios*meses_anio -> 49800
A43: Ingresos: API nivel superior (Agencias) | C43: =C34*INDEX(precio_agencias,1,$B$2)*sens_precios*meses_anio -> 108000 | D43: =D34*INDEX(precio_agencias,1,$B$2)*sens_precios*meses_anio -> 306000 | E43: =E34*INDEX(precio_agencias,1,$B$2)*sens_precios*meses_anio -> 450000 | F43: =F34*INDEX(precio_agencias,1,$B$2)*sens_precios*meses_anio -> 558000 | G43: =G34*INDEX(precio_agencias,1,$B$2)*sens_precios*meses_anio -> 648000
A44: Ingresos: reportes de monitoreo electoral, organismos y ONG | C44: =C35*INDEX(precio_organismos,1,$B$2)*sens_precios -> 90000 | D44: =D35*INDEX(precio_organismos,1,$B$2)*sens_precios -> 0 | E44: =E35*INDEX(precio_organismos,1,$B$2)*sens_precios -> 90000 | F44: =F35*INDEX(precio_organismos,1,$B$2)*sens_precios -> 0 | G44: =G35*INDEX(precio_organismos,1,$B$2)*sens_precios -> 90000
A45: Ingresos totales | B45: =SUM(B39:B44) -> 0 | C45: =SUM(C39:C44) -> 255000 | D45: =SUM(D39:D44) -> 473400 | E45: =SUM(E39:E44) -> 791400 | F45: =SUM(F39:F44) -> 849000 | G45: =SUM(G39:G44) -> 1045800
A47: Costos por rubro
A48: Costo: recursos humanos (desarrollador semi senior, con cargas sociales) | C48: =sueldo_usd*sueldos_por_anio*(1+cargas_sociales)*(1+ajuste_sueldo)^C$3 -> 30786.21 | D48: =sueldo_usd*sueldos_por_anio*(1+cargas_sociales)*(1+ajuste_sueldo)^D$3 -> 32325.52 | E48: =sueldo_usd*sueldos_por_anio*(1+cargas_sociales)*(1+ajuste_sueldo)^E$3 -> 33941.797 | F48: =sueldo_usd*sueldos_por_anio*(1+cargas_sociales)*(1+ajuste_sueldo)^F$3 -> 35638.886 | G48: =sueldo_usd*sueldos_por_anio*(1+cargas_sociales)*(1+ajuste_sueldo)^G$3 -> 37420.831
A49: Costo: infraestructura | B49: =inv_infraestructura_0 -> 156 | C49: =meses_anio*(infra_base+infra_escalado*C6/ua_escalado)+dominio_anual -> 305.5 | D49: =meses_anio*(infra_base+infra_escalado*D6/ua_escalado)+dominio_anual -> 485.5 | E49: =meses_anio*(infra_base+infra_escalado*E6/ua_escalado)+dominio_anual -> 845.5 | F49: =meses_anio*(infra_base+infra_escalado*F6/ua_escalado)+dominio_anual -> 1445.5 | G49: =meses_anio*(infra_base+infra_escalado*G6/ua_escalado)+dominio_anual -> 2045.5
A50: Costo: marketing | C50: =INDEX(marketing,C$3,$B$2) -> 6000 | D50: =INDEX(marketing,D$3,$B$2) -> 9000 | E50: =INDEX(marketing,E$3,$B$2) -> 12000 | F50: =INDEX(marketing,F$3,$B$2) -> 15000 | G50: =INDEX(marketing,G$3,$B$2) -> 18000
A51: Costo: dominio, marca y asesoría legal | B51: =inv_dominio+inv_marca_inpi+inv_legal -> 1558.5
A52: Costo variable: análisis de usuarios gratuitos | C52: =C6*MIN(INDEX(analisis_por_ua_mes,1,$B$2),tope_mensual)*meses_anio*(1-INDEX(tasa_reuso,1,$B$2))*INDEX(costo_analisis,1,$B$2)*sens_costo_analisis -> 2293.92 | D52: =D6*MIN(INDEX(analisis_por_ua_mes,1,$B$2),tope_mensual)*meses_anio*(1-INDEX(tasa_reuso,1,$B$2))*INDEX(costo_analisis,1,$B$2)*sens_costo_analisis -> 9175.68 | E52: =E6*MIN(INDEX(analisis_por_ua_mes,1,$B$2),tope_mensual)*meses_anio*(1-INDEX(tasa_reuso,1,$B$2))*INDEX(costo_analisis,1,$B$2)*sens_costo_analisis -> 22939.2 | F52: =F6*MIN(INDEX(analisis_por_ua_mes,1,$B$2),tope_mensual)*meses_anio*(1-INDEX(tasa_reuso,1,$B$2))*INDEX(costo_analisis,1,$B$2)*sens_costo_analisis -> 45878.4 | G52: =G6*MIN(INDEX(analisis_por_ua_mes,1,$B$2),tope_mensual)*meses_anio*(1-INDEX(tasa_reuso,1,$B$2))*INDEX(costo_analisis,1,$B$2)*sens_costo_analisis -> 68817.6
A53: Costo variable: consultas de la API B2B | C53: =((C19+C24)*MIN(INDEX(consultas_pro_mes,1,$B$2),cuota_intermedia)+(C14+C34)*MIN(INDEX(consultas_ent_mes,1,$B$2),cuota_superior))*meses_anio*(1-INDEX(tasa_reuso,1,$B$2))*INDEX(costo_analisis,1,$B$2)*sens_costo_analisis -> 8258.112 | D53: =((D19+D24)*MIN(INDEX(consultas_pro_mes,1,$B$2),cuota_intermedia)+(D14+D34)*MIN(INDEX(consultas_ent_mes,1,$B$2),cuota_superior))*meses_anio*(1-INDEX(tasa_reuso,1,$B$2))*INDEX(costo_analisis,1,$B$2)*sens_costo_analisis -> 23673.254 | E53: =((E19+E24)*MIN(INDEX(consultas_pro_mes,1,$B$2),cuota_intermedia)+(E14+E34)*MIN(INDEX(consultas_ent_mes,1,$B$2),cuota_superior))*meses_anio*(1-INDEX(tasa_reuso,1,$B$2))*INDEX(costo_analisis,1,$B$2)*sens_costo_analisis -> 35051.098 | F53: =((F19+F24)*MIN(INDEX(consultas_pro_mes,1,$B$2),cuota_intermedia)+(F14+F34)*MIN(INDEX(consultas_ent_mes,1,$B$2),cuota_superior))*meses_anio*(1-INDEX(tasa_reuso,1,$B$2))*INDEX(costo_analisis,1,$B$2)*sens_costo_analisis -> 42391.642 | G53: =((G19+G24)*MIN(INDEX(consultas_pro_mes,1,$B$2),cuota_intermedia)+(G14+G34)*MIN(INDEX(consultas_ent_mes,1,$B$2),cuota_superior))*meses_anio*(1-INDEX(tasa_reuso,1,$B$2))*INDEX(costo_analisis,1,$B$2)*sens_costo_analisis -> 47621.779
A54: Costos totales | B54: =SUM(B48:B53) -> 1714.5 | C54: =SUM(C48:C53) -> 47643.742 | D54: =SUM(D48:D53) -> 74659.955 | E54: =SUM(E48:E53) -> 104777.59 | F54: =SUM(F48:F53) -> 140354.43 | G54: =SUM(G48:G53) -> 173905.71
A56: Impuesto y capital de trabajo
A57: Resultado antes de impuestos | B57: =B45-B54 -> -1714.5 | C57: =C45-C54 -> 207356.26 | D57: =D45-D54 -> 398740.05 | E57: =E45-E54 -> 686622.41 | F57: =F45-F54 -> 708645.57 | G57: =G45-G54 -> 871894.29
A58: Quebranto acumulado | B58: =MIN(0,B57) -> -1714.5 | C58: =MIN(0,B58+C57) -> 0 | D58: =MIN(0,C58+D57) -> 0 | E58: =MIN(0,D58+E57) -> 0 | F58: =MIN(0,E58+F57) -> 0 | G58: =MIN(0,F58+G57) -> 0
A59: Impuesto a las ganancias | B59: =alicuota_ganancias*MAX(0,B57) -> 0 | C59: =alicuota_ganancias*MAX(0,B58+C57) -> 71974.615 | D59: =alicuota_ganancias*MAX(0,C58+D57) -> 139559.02 | E59: =alicuota_ganancias*MAX(0,D58+E57) -> 240317.84 | F59: =alicuota_ganancias*MAX(0,E58+F57) -> 248025.95 | G59: =alicuota_ganancias*MAX(0,F58+G57) -> 305163
A60: Capital de trabajo | B60: =meses_cobro/meses_anio*B45 -> 0 | C60: =meses_cobro/meses_anio*C45 -> 42500 | D60: =meses_cobro/meses_anio*D45 -> 78900 | E60: =meses_cobro/meses_anio*E45 -> 131900 | F60: =meses_cobro/meses_anio*F45 -> 141500 | G60: =meses_cobro/meses_anio*G45 -> 174300
A61: Capital de trabajo: variación | B61: =B60 -> 0 | C61: =C60-B60 -> 42500 | D61: =D60-C60 -> 36400 | E61: =E60-D60 -> 53000 | F61: =F60-E60 -> 9600 | G61: =G60-F60 -> 32800
A62: Recupero del capital de trabajo | G62: =G60 -> 174300
A64: Flujo de caja
A65: Flujo neto | B65: =B57-B59-B61+N(B62) -> -1714.5 | C65: =C57-C59-C61+N(C62) -> 92881.643 | D65: =D57-D59-D61+N(D62) -> 222781.03 | E65: =E57-E59-E61+N(E62) -> 393304.56 | F65: =F57-F59-F61+N(F62) -> 451019.62 | G65: =G57-G59-G61+N(G62) -> 708231.29
A66: Factor de descuento | B66: =1/(1+tasa_descuento)^B$3 -> 1 | C66: =1/(1+tasa_descuento)^C$3 -> 0.8 | D66: =1/(1+tasa_descuento)^D$3 -> 0.64 | E66: =1/(1+tasa_descuento)^E$3 -> 0.512 | F66: =1/(1+tasa_descuento)^F$3 -> 0.4096 | G66: =1/(1+tasa_descuento)^G$3 -> 0.32768
A67: Flujo descontado | B67: =B65*B66 -> -1714.5 | C67: =C65*C66 -> 74305.314 | D67: =D65*D66 -> 142579.86 | E67: =E65*E66 -> 201371.94 | F67: =F65*F66 -> 184737.64 | G67: =G65*G66 -> 232073.23
A68: Flujo neto acumulado | B68: =B65 -> -1714.5 | C68: =B68+C65 -> 91167.143 | D68: =C68+D65 -> 313948.17 | E68: =D68+E65 -> 707252.74 | F68: =E68+F65 -> 1158272.4 | G68: =F68+G65 -> 1866503.6
A69: Flujo descontado acumulado | B69: =B67 -> -1714.5 | C69: =B69+C67 -> 72590.814 | D69: =C69+D67 -> 215170.67 | E69: =D69+E67 -> 416542.61 | F69: =E69+F67 -> 601280.25 | G69: =F69+G67 -> 833353.48
A70: Recupero simple: a + b/c en el año del cruce | C70: =IF(AND(B68<0,C68>=0),C$3-1+(-B68)/C65,"") -> 0.018458976 | D70: =IF(AND(C68<0,D68>=0),D$3-1+(-C68)/D65,"") | E70: =IF(AND(D68<0,E68>=0),E$3-1+(-D68)/E65,"") | F70: =IF(AND(E68<0,F68>=0),F$3-1+(-E68)/F65,"") | G70: =IF(AND(F68<0,G68>=0),G$3-1+(-F68)/G65,"")
A71: Recupero descontado: a + b/c en el año del cruce | C71: =IF(AND(B69<0,C69>=0),C$3-1+(-B69)/C67,"") -> 0.02307372 | D71: =IF(AND(C69<0,D69>=0),D$3-1+(-C69)/D67,"") | E71: =IF(AND(D69<0,E69>=0),E$3-1+(-D69)/E67,"") | F71: =IF(AND(E69<0,F69>=0),F$3-1+(-E69)/F67,"") | G71: =IF(AND(F69<0,G69>=0),G$3-1+(-F69)/G67,"")
A73: Indicadores
A74: VAN (USD) | B74: =SUM(B67:G67) -> 833353.48
A75: TIR | B75: =IFERROR(IRR(B65:G65),"no definida") -> 55.545393
A76: Payback simple (años) | B76: =IF(COUNT(C70:G70)=0,"no se recupera",MIN(C70:G70)) -> 0.018458976
A77: Payback descontado (años) | B77: =IF(COUNT(C71:G71)=0,"no se recupera",MIN(C71:G71)) -> 0.02307372
A78: VAN con valor residual (USD) | B78: =SUM(B67:G67)+MAX(0,G65-G62)*(1+crecimiento_perpetuo)/(tasa_descuento-crecimiento_perpetuo)/(1+tasa_descuento)^5 -> 1609256.9
A79: Ingreso medio por cliente B2B en el año 5 (USD) | B79: =IFERROR(G45/G36,"no definido") -> 10781.443
A80: Punto de equilibrio (clientes B2B) | B80: =IFERROR(ROUNDUP(G54/B79,0),"no definido") -> 17

Sheet Neutral
A1: Escenario neutral (USD nominales; todo lo derivado es fórmula)
A2: Columna de escenario en Supuestos (1 = optimista, 2 = neutral, 3 = pesimista) | B2: 2
A3: Año | B3: =COLUMN()-2 -> 0 | C3: =COLUMN()-2 -> 1 | D3: =COLUMN()-2 -> 2 | E3: =COLUMN()-2 -> 3 | F3: =COLUMN()-2 -> 4 | G3: =COLUMN()-2 -> 5
A4: Año calendario | B4: =anio_0+B$3 -> 2026 | C4: =anio_0+C$3 -> 2027 | D4: =anio_0+D$3 -> 2028 | E4: =anio_0+E$3 -> 2029 | F4: =anio_0+F$3 -> 2030 | G4: =anio_0+G$3 -> 2031
A5: Año electoral (1 = sí) | B5: =INDEX(anio_electoral,B$3+1) -> 0 | C5: =INDEX(anio_electoral,C$3+1) -> 1 | D5: =INDEX(anio_electoral,D$3+1) -> 0 | E5: =INDEX(anio_electoral,E$3+1) -> 1 | F5: =INDEX(anio_electoral,F$3+1) -> 0 | G5: =INDEX(anio_electoral,G$3+1) -> 1
A6: Usuarios activos mensuales | C6: =INDEX(usuarios_activos,C$3,$B$2) -> 2000 | D6: =INDEX(usuarios_activos,D$3,$B$2) -> 8000 | E6: =INDEX(usuarios_activos,E$3,$B$2) -> 20000 | F6: =INDEX(usuarios_activos,F$3,$B$2) -> 40000 | G6: =INDEX(usuarios_activos,G$3,$B$2) -> 60000
A7: Ventas B2B habilitadas (1 = sí) | C7: =IF(C6>=ua_inicio_b2b,1,0) -> 0 | D7: =IF(D6>=ua_inicio_b2b,1,0) -> 1 | E7: =IF(E6>=ua_inicio_b2b,1,0) -> 1 | F7: =IF(F6>=ua_inicio_b2b,1,0) -> 1 | G7: =IF(G6>=ua_inicio_b2b,1,0) -> 1
A9: Clientes B2B
A10: Medios de gran porte: activos al inicio | C10: =N(B13) -> 0 | D10: =N(C13) -> 0 | E10: =N(D13) -> 1 | F10: =N(E13) -> 2 | G10: =N(F13) -> 3
A11: Medios de gran porte: bajas | C11: =ROUND(INDEX(churn_medios_grandes,1,$B$2)*C10,0) -> 0 | D11: =ROUND(INDEX(churn_medios_grandes,1,$B$2)*D10,0) -> 0 | E11: =ROUND(INDEX(churn_medios_grandes,1,$B$2)*E10,0) -> 0 | F11: =ROUND(INDEX(churn_medios_grandes,1,$B$2)*F10,0) -> 0 | G11: =ROUND(INDEX(churn_medios_grandes,1,$B$2)*G10,0) -> 0
A12: Medios de gran porte: altas | C12: =C7*ROUND(INDEX(capt_medios_grandes,1,$B$2)*sens_captacion*(u_medios_grandes-C10),0) -> 0 | D12: =D7*ROUND(INDEX(capt_medios_grandes,1,$B$2)*sens_captacion*(u_medios_grandes-D10),0) -> 1 | E12: =E7*ROUND(INDEX(capt_medios_grandes,1,$B$2)*sens_captacion*(u_medios_grandes-E10),0) -> 1 | F12: =F7*ROUND(INDEX(capt_medios_grandes,1,$B$2)*sens_captacion*(u_medios_grandes-F10),0) -> 1 | G12: =G7*ROUND(INDEX(capt_medios_grandes,1,$B$2)*sens_captacion*(u_medios_grandes-G10),0) -> 1
A13: Medios de gran porte: activos al cierre | C13: =C10+C12-C11 -> 0 | D13: =D10+D12-D11 -> 1 | E13: =E10+E12-E11 -> 2 | F13: =F10+F12-F11 -> 3 | G13: =G10+G12-G11 -> 4
A14: Medios de gran porte: promedio del año | C14: =(C10+C13)/2 -> 0 | D14: =(D10+D13)/2 -> 0.5 | E14: =(E10+E13)/2 -> 1.5 | F14: =(F10+F13)/2 -> 2.5 | G14: =(G10+G13)/2 -> 3.5
A15: Medios socios de ADEPA (resto): activos al inicio | C15: =N(B18) -> 0 | D15: =N(C18) -> 0 | E15: =N(D18) -> 5 | F15: =N(E18) -> 8 | G15: =N(F18) -> 10
A16: Medios socios de ADEPA (resto): bajas | C16: =ROUND(INDEX(churn_medios_chicos,1,$B$2)*C15,0) -> 0 | D16: =ROUND(INDEX(churn_medios_chicos,1,$B$2)*D15,0) -> 0 | E16: =ROUND(INDEX(churn_medios_chicos,1,$B$2)*E15,0) -> 1 | F16: =ROUND(INDEX(churn_medios_chicos,1,$B$2)*F15,0) -> 2 | G16: =ROUND(INDEX(churn_medios_chicos,1,$B$2)*G15,0) -> 2
A17: Medios socios de ADEPA (resto): altas | C17: =C7*ROUND(INDEX(capt_medios_chicos,1,$B$2)*sens_captacion*(u_medios_chicos-C15),0) -> 0 | D17: =D7*ROUND(INDEX(capt_medios_chicos,1,$B$2)*sens_captacion*(u_medios_chicos-D15),0) -> 5 | E17: =E7*ROUND(INDEX(capt_medios_chicos,1,$B$2)*sens_captacion*(u_medios_chicos-E15),0) -> 4 | F17: =F7*ROUND(INDEX(capt_medios_chicos,1,$B$2)*sens_captacion*(u_medios_chicos-F15),0) -> 4 | G17: =G7*ROUND(INDEX(capt_medios_chicos,1,$B$2)*sens_captacion*(u_medios_chicos-G15),0) -> 4
A18: Medios socios de ADEPA (resto): activos al cierre | C18: =C15+C17-C16 -> 0 | D18: =D15+D17-D16 -> 5 | E18: =E15+E17-E16 -> 8 | F18: =F15+F17-F16 -> 10 | G18: =G15+G17-G16 -> 12
A19: Medios socios de ADEPA (resto): promedio del año | C19: =(C15+C18)/2 -> 0 | D19: =(D15+D18)/2 -> 2.5 | E19: =(E15+E18)/2 -> 6.5 | F19: =(F15+F18)/2 -> 9 | G19: =(G15+G18)/2 -> 11
A20: Verificadores: activos al inicio | C20: =N(B23) -> 0 | D20: =N(C23) -> 0 | E20: =N(D23) -> 1 | F20: =N(E23) -> 2 | G20: =N(F23) -> 2
A21: Verificadores: bajas | C21: =ROUND(INDEX(churn_verificadores,1,$B$2)*C20,0) -> 0 | D21: =ROUND(INDEX(churn_verificadores,1,$B$2)*D20,0) -> 0 | E21: =ROUND(INDEX(churn_verificadores,1,$B$2)*E20,0) -> 0 | F21: =ROUND(INDEX(churn_verificadores,1,$B$2)*F20,0) -> 0 | G21: =ROUND(INDEX(churn_verificadores,1,$B$2)*G20,0) -> 0
A22: Verificadores: altas | C22: =C7*ROUND(INDEX(capt_verificadores,1,$B$2)*sens_captacion*(u_verificadores-C20),0) -> 0 | D22: =D7*ROUND(INDEX(capt_verificadores,1,$B$2)*sens_captacion*(u_verificadores-D20),0) -> 1 | E22: =E7*ROUND(INDEX(capt_verificadores,1,$B$2)*sens_captacion*(u_verificadores-E20),0) -> 1 | F22: =F7*ROUND(INDEX(capt_verificadores,1,$B$2)*sens_captacion*(u_verificadores-F20),0) -> 0 | G22: =G7*ROUND(INDEX(capt_verificadores,1,$B$2)*sens_captacion*(u_verificadores-G20),0) -> 0
A23: Verificadores: activos al cierre | C23: =C20+C22-C21 -> 0 | D23: =D20+D22-D21 -> 1 | E23: =E20+E22-E21 -> 2 | F23: =F20+F22-F21 -> 2 | G23: =G20+G22-G21 -> 2
A24: Verificadores: promedio del año | C24: =(C20+C23)/2 -> 0 | D24: =(D20+D23)/2 -> 0.5 | E24: =(E20+E23)/2 -> 1.5 | F24: =(F20+F23)/2 -> 2 | G24: =(G20+G23)/2 -> 2
A25: Universidades y observatorios: activos al inicio | C25: =N(B28) -> 0 | D25: =N(C28) -> 0 | E25: =N(D28) -> 6 | F25: =N(E28) -> 11 | G25: =N(F28) -> 16
A26: Universidades y observatorios: bajas | C26: =ROUND(INDEX(churn_universidades,1,$B$2)*C25,0) -> 0 | D26: =ROUND(INDEX(churn_universidades,1,$B$2)*D25,0) -> 0 | E26: =ROUND(INDEX(churn_universidades,1,$B$2)*E25,0) -> 1 | F26: =ROUND(INDEX(churn_universidades,1,$B$2)*F25,0) -> 1 | G26: =ROUND(INDEX(churn_universidades,1,$B$2)*G25,0) -> 2
A27: Universidades y observatorios: altas | C27: =C7*ROUND(INDEX(capt_universidades,1,$B$2)*sens_captacion*(u_universidades-C25),0) -> 0 | D27: =D7*ROUND(INDEX(capt_universidades,1,$B$2)*sens_captacion*(u_universidades-D25),0) -> 6 | E27: =E7*ROUND(INDEX(capt_universidades,1,$B$2)*sens_captacion*(u_universidades-E25),0) -> 6 | F27: =F7*ROUND(INDEX(capt_universidades,1,$B$2)*sens_captacion*(u_universidades-F25),0) -> 6 | G27: =G7*ROUND(INDEX(capt_universidades,1,$B$2)*sens_captacion*(u_universidades-G25),0) -> 5
A28: Universidades y observatorios: activos al cierre | C28: =C25+C27-C26 -> 0 | D28: =D25+D27-D26 -> 6 | E28: =E25+E27-E26 -> 11 | F28: =F25+F27-F26 -> 16 | G28: =G25+G27-G26 -> 19
A29: Universidades y observatorios: promedio del año | C29: =(C25+C28)/2 -> 0 | D29: =(D25+D28)/2 -> 3 | E29: =(E25+E28)/2 -> 8.5 | F29: =(F25+F28)/2 -> 13.5 | G29: =(G25+G28)/2 -> 17.5
A30: Agencias: activos al inicio | C30: =N(B33) -> 0 | D30: =N(C33) -> 0 | E30: =N(D33) -> 2 | F30: =N(E33) -> 4 | G30: =N(F33) -> 5
A31: Agencias: bajas | C31: =ROUND(INDEX(churn_agencias,1,$B$2)*C30,0) -> 0 | D31: =ROUND(INDEX(churn_agencias,1,$B$2)*D30,0) -> 0 | E31: =ROUND(INDEX(churn_agencias,1,$B$2)*E30,0) -> 0 | F31: =ROUND(INDEX(churn_agencias,1,$B$2)*F30,0) -> 1 | G31: =ROUND(INDEX(churn_agencias,1,$B$2)*G30,0) -> 1
A32: Agencias: altas | C32: =C7*ROUND(INDEX(capt_agencias,1,$B$2)*sens_captacion*(u_agencias-C30),0) -> 0 | D32: =D7*ROUND(INDEX(capt_agencias,1,$B$2)*sens_captacion*(u_agencias-D30),0) -> 2 | E32: =E7*ROUND(INDEX(capt_agencias,1,$B$2)*sens_captacion*(u_agencias-E30),0) -> 2 | F32: =F7*ROUND(INDEX(capt_agencias,1,$B$2)*sens_captacion*(u_agencias-F30),0) -> 2 | G32: =G7*ROUND(INDEX(capt_agencias,1,$B$2)*sens_captacion*(u_agencias-G30),0) -> 2
A33: Agencias: activos al cierre | C33: =C30+C32-C31 -> 0 | D33: =D30+D32-D31 -> 2 | E33: =E30+E32-E31 -> 4 | F33: =F30+F32-F31 -> 5 | G33: =G30+G32-G31 -> 6
A34: Agencias: promedio del año | C34: =(C30+C33)/2 -> 0 | D34: =(D30+D33)/2 -> 1 | E34: =(E30+E33)/2 -> 3 | F34: =(F30+F33)/2 -> 4.5 | G34: =(G30+G33)/2 -> 5.5
A35: Organismos y ONG: contratos | C35: =C5*C7*ROUND(INDEX(capt_organismos,1,$B$2)*sens_captacion*u_organismos,0) -> 0 | D35: =D5*D7*ROUND(INDEX(capt_organismos,1,$B$2)*sens_captacion*u_organismos,0) -> 0 | E35: =E5*E7*ROUND(INDEX(capt_organismos,1,$B$2)*sens_captacion*u_organismos,0) -> 2 | F35: =F5*F7*ROUND(INDEX(capt_organismos,1,$B$2)*sens_captacion*u_organismos,0) -> 0 | G35: =G5*G7*ROUND(INDEX(capt_organismos,1,$B$2)*sens_captacion*u_organismos,0) -> 2
A36: Clientes B2B (promedio del año, con contratos) | C36: =C14+C19+C24+C29+C34+C35 -> 0 | D36: =D14+D19+D24+D29+D34+D35 -> 7.5 | E36: =E14+E19+E24+E29+E34+E35 -> 23 | F36: =F14+F19+F24+F29+F34+F35 -> 31.5 | G36: =G14+G19+G24+G29+G34+G35 -> 41.5
A38: Ingresos por producto
A39: Ingresos: API nivel superior (Medios de gran porte) | C39: =C14*INDEX(precio_medios_grandes,1,$B$2)*sens_precios*meses_anio -> 0 | D39: =D14*INDEX(precio_medios_grandes,1,$B$2)*sens_precios*meses_anio -> 15000 | E39: =E14*INDEX(precio_medios_grandes,1,$B$2)*sens_precios*meses_anio -> 45000 | F39: =F14*INDEX(precio_medios_grandes,1,$B$2)*sens_precios*meses_anio -> 75000 | G39: =G14*INDEX(precio_medios_grandes,1,$B$2)*sens_precios*meses_anio -> 105000
A40: Ingresos: API nivel intermedio (Medios socios de ADEPA (resto)) | C40: =C19*precio_medios_chicos*sens_precios*meses_anio -> 0 | D40: =D19*precio_medios_chicos*sens_precios*meses_anio -> 6000 | E40: =E19*precio_medios_chicos*sens_precios*meses_anio -> 15600 | F40: =F19*precio_medios_chicos*sens_precios*meses_anio -> 21600 | G40: =G19*precio_medios_chicos*sens_precios*meses_anio -> 26400
A41: Ingresos: panel de tendencias y API intermedia (Verificadores) | C41: =C24*precio_verificadores*sens_precios*meses_anio -> 0 | D41: =D24*precio_verificadores*sens_precios*meses_anio -> 3000 | E41: =E24*precio_verificadores*sens_precios*meses_anio -> 9000 | F41: =F24*precio_verificadores*sens_precios*meses_anio -> 12000 | G41: =G24*precio_verificadores*sens_precios*meses_anio -> 12000
A42: Ingresos: acceso histórico (Universidades y observatorios) | C42: =C29*precio_universidades*sens_precios*meses_anio -> 0 | D42: =D29*precio_universidades*sens_precios*meses_anio -> 3600 | E42: =E29*precio_universidades*sens_precios*meses_anio -> 10200 | F42: =F29*precio_universidades*sens_precios*meses_anio -> 16200 | G42: =G29*precio_universidades*sens_precios*meses_anio -> 21000
A43: Ingresos: API nivel superior (Agencias) | C43: =C34*INDEX(precio_agencias,1,$B$2)*sens_precios*meses_anio -> 0 | D43: =D34*INDEX(precio_agencias,1,$B$2)*sens_precios*meses_anio -> 30000 | E43: =E34*INDEX(precio_agencias,1,$B$2)*sens_precios*meses_anio -> 90000 | F43: =F34*INDEX(precio_agencias,1,$B$2)*sens_precios*meses_anio -> 135000 | G43: =G34*INDEX(precio_agencias,1,$B$2)*sens_precios*meses_anio -> 165000
A44: Ingresos: reportes de monitoreo electoral, organismos y ONG | C44: =C35*INDEX(precio_organismos,1,$B$2)*sens_precios -> 0 | D44: =D35*INDEX(precio_organismos,1,$B$2)*sens_precios -> 0 | E44: =E35*INDEX(precio_organismos,1,$B$2)*sens_precios -> 40000 | F44: =F35*INDEX(precio_organismos,1,$B$2)*sens_precios -> 0 | G44: =G35*INDEX(precio_organismos,1,$B$2)*sens_precios -> 40000
A45: Ingresos totales | B45: =SUM(B39:B44) -> 0 | C45: =SUM(C39:C44) -> 0 | D45: =SUM(D39:D44) -> 57600 | E45: =SUM(E39:E44) -> 209800 | F45: =SUM(F39:F44) -> 259800 | G45: =SUM(G39:G44) -> 369400
A47: Costos por rubro
A48: Costo: recursos humanos (desarrollador semi senior, con cargas sociales) | C48: =sueldo_usd*sueldos_por_anio*(1+cargas_sociales)*(1+ajuste_sueldo)^C$3 -> 30786.21 | D48: =sueldo_usd*sueldos_por_anio*(1+cargas_sociales)*(1+ajuste_sueldo)^D$3 -> 32325.52 | E48: =sueldo_usd*sueldos_por_anio*(1+cargas_sociales)*(1+ajuste_sueldo)^E$3 -> 33941.797 | F48: =sueldo_usd*sueldos_por_anio*(1+cargas_sociales)*(1+ajuste_sueldo)^F$3 -> 35638.886 | G48: =sueldo_usd*sueldos_por_anio*(1+cargas_sociales)*(1+ajuste_sueldo)^G$3 -> 37420.831
A49: Costo: infraestructura | B49: =inv_infraestructura_0 -> 156 | C49: =meses_anio*(infra_base+infra_escalado*C6/ua_escalado)+dominio_anual -> 269.5 | D49: =meses_anio*(infra_base+infra_escalado*D6/ua_escalado)+dominio_anual -> 341.5 | E49: =meses_anio*(infra_base+infra_escalado*E6/ua_escalado)+dominio_anual -> 485.5 | F49: =meses_anio*(infra_base+infra_escalado*F6/ua_escalado)+dominio_anual -> 725.5 | G49: =meses_anio*(infra_base+infra_escalado*G6/ua_escalado)+dominio_anual -> 965.5
A50: Costo: marketing | C50: =INDEX(marketing,C$3,$B$2) -> 4000 | D50: =INDEX(marketing,D$3,$B$2) -> 6000 | E50: =INDEX(marketing,E$3,$B$2) -> 8000 | F50: =INDEX(marketing,F$3,$B$2) -> 10000 | G50: =INDEX(marketing,G$3,$B$2) -> 12000
A51: Costo: dominio, marca y asesoría legal | B51: =inv_dominio+inv_marca_inpi+inv_legal -> 1558.5
A52: Costo variable: análisis de usuarios gratuitos | C52: =C6*MIN(INDEX(analisis_por_ua_mes,1,$B$2),tope_mensual)*meses_anio*(1-INDEX(tasa_reuso,1,$B$2))*INDEX(costo_analisis,1,$B$2)*sens_costo_analisis -> 2070.096 | D52: =D6*MIN(INDEX(analisis_por_ua_mes,1,$B$2),tope_mensual)*meses_anio*(1-INDEX(tasa_reuso,1,$B$2))*INDEX(costo_analisis,1,$B$2)*sens_costo_analisis -> 8280.384 | E52: =E6*MIN(INDEX(analisis_por_ua_mes,1,$B$2),tope_mensual)*meses_anio*(1-INDEX(tasa_reuso,1,$B$2))*INDEX(costo_analisis,1,$B$2)*sens_costo_analisis -> 20700.96 | F52: =F6*MIN(INDEX(analisis_por_ua_mes,1,$B$2),tope_mensual)*meses_anio*(1-INDEX(tasa_reuso,1,$B$2))*INDEX(costo_analisis,1,$B$2)*sens_costo_analisis -> 41401.92 | G52: =G6*MIN(INDEX(analisis_por_ua_mes,1,$B$2),tope_mensual)*meses_anio*(1-INDEX(tasa_reuso,1,$B$2))*INDEX(costo_analisis,1,$B$2)*sens_costo_analisis -> 62102.88
A53: Costo variable: consultas de la API B2B | C53: =((C19+C24)*MIN(INDEX(consultas_pro_mes,1,$B$2),cuota_intermedia)+(C14+C34)*MIN(INDEX(consultas_ent_mes,1,$B$2),cuota_superior))*meses_anio*(1-INDEX(tasa_reuso,1,$B$2))*INDEX(costo_analisis,1,$B$2)*sens_costo_analisis -> 0 | D53: =((D19+D24)*MIN(INDEX(consultas_pro_mes,1,$B$2),cuota_intermedia)+(D14+D34)*MIN(INDEX(consultas_ent_mes,1,$B$2),cuota_superior))*meses_anio*(1-INDEX(tasa_reuso,1,$B$2))*INDEX(costo_analisis,1,$B$2)*sens_costo_analisis -> 14904.691 | E53: =((E19+E24)*MIN(INDEX(consultas_pro_mes,1,$B$2),cuota_intermedia)+(E14+E34)*MIN(INDEX(consultas_ent_mes,1,$B$2),cuota_superior))*meses_anio*(1-INDEX(tasa_reuso,1,$B$2))*INDEX(costo_analisis,1,$B$2)*sens_costo_analisis -> 43886.035 | F53: =((F19+F24)*MIN(INDEX(consultas_pro_mes,1,$B$2),cuota_intermedia)+(F14+F34)*MIN(INDEX(consultas_ent_mes,1,$B$2),cuota_superior))*meses_anio*(1-INDEX(tasa_reuso,1,$B$2))*INDEX(costo_analisis,1,$B$2)*sens_costo_analisis -> 67071.11 | G53: =((G19+G24)*MIN(INDEX(consultas_pro_mes,1,$B$2),cuota_intermedia)+(G14+G34)*MIN(INDEX(consultas_ent_mes,1,$B$2),cuota_superior))*meses_anio*(1-INDEX(tasa_reuso,1,$B$2))*INDEX(costo_analisis,1,$B$2)*sens_costo_analisis -> 85287.955
A54: Costos totales | B54: =SUM(B48:B53) -> 1714.5 | C54: =SUM(C48:C53) -> 37125.806 | D54: =SUM(D48:D53) -> 61852.096 | E54: =SUM(E48:E53) -> 107014.29 | F54: =SUM(F48:F53) -> 154837.42 | G54: =SUM(G48:G53) -> 197777.17
A56: Impuesto y capital de trabajo
A57: Resultado antes de impuestos | B57: =B45-B54 -> -1714.5 | C57: =C45-C54 -> -37125.806 | D57: =D45-D54 -> -4252.0957 | E57: =E45-E54 -> 102785.71 | F57: =F45-F54 -> 104962.58 | G57: =G45-G54 -> 171622.83
A58: Quebranto acumulado | B58: =MIN(0,B57) -> -1714.5 | C58: =MIN(0,B58+C57) -> -38840.306 | D58: =MIN(0,C58+D57) -> -43092.402 | E58: =MIN(0,D58+E57) -> 0 | F58: =MIN(0,E58+F57) -> 0 | G58: =MIN(0,F58+G57) -> 0
A59: Impuesto a las ganancias | B59: =alicuota_ganancias*MAX(0,B57) -> 0 | C59: =alicuota_ganancias*MAX(0,B58+C57) -> 0 | D59: =alicuota_ganancias*MAX(0,C58+D57) -> 0 | E59: =alicuota_ganancias*MAX(0,D58+E57) -> 20892.657 | F59: =alicuota_ganancias*MAX(0,E58+F57) -> 36736.904 | G59: =alicuota_ganancias*MAX(0,F58+G57) -> 60067.992
A60: Capital de trabajo | B60: =meses_cobro/meses_anio*B45 -> 0 | C60: =meses_cobro/meses_anio*C45 -> 0 | D60: =meses_cobro/meses_anio*D45 -> 9600 | E60: =meses_cobro/meses_anio*E45 -> 34966.667 | F60: =meses_cobro/meses_anio*F45 -> 43300 | G60: =meses_cobro/meses_anio*G45 -> 61566.667
A61: Capital de trabajo: variación | B61: =B60 -> 0 | C61: =C60-B60 -> 0 | D61: =D60-C60 -> 9600 | E61: =E60-D60 -> 25366.667 | F61: =F60-E60 -> 8333.3333 | G61: =G60-F60 -> 18266.667
A62: Recupero del capital de trabajo | G62: =G60 -> 61566.667
A64: Flujo de caja
A65: Flujo neto | B65: =B57-B59-B61+N(B62) -> -1714.5 | C65: =C57-C59-C61+N(C62) -> -37125.806 | D65: =D57-D59-D61+N(D62) -> -13852.096 | E65: =E57-E59-E61+N(E62) -> 56526.384 | F65: =F57-F59-F61+N(F62) -> 59892.346 | G65: =G57-G59-G61+N(G62) -> 154854.84
A66: Factor de descuento | B66: =1/(1+tasa_descuento)^B$3 -> 1 | C66: =1/(1+tasa_descuento)^C$3 -> 0.8 | D66: =1/(1+tasa_descuento)^D$3 -> 0.64 | E66: =1/(1+tasa_descuento)^E$3 -> 0.512 | F66: =1/(1+tasa_descuento)^F$3 -> 0.4096 | G66: =1/(1+tasa_descuento)^G$3 -> 0.32768
A67: Flujo descontado | B67: =B65*B66 -> -1714.5 | C67: =C65*C66 -> -29700.645 | D67: =D65*D66 -> -8865.3412 | E67: =E65*E66 -> 28941.509 | F67: =F65*F66 -> 24531.905 | G67: =G65*G66 -> 50742.835
A68: Flujo neto acumulado | B68: =B65 -> -1714.5 | C68: =B68+C65 -> -38840.306 | D68: =C68+D65 -> -52692.402 | E68: =D68+E65 -> 3833.9826 | F68: =E68+F65 -> 63726.328 | G68: =F68+G65 -> 218581.17
A69: Flujo descontado acumulado | B69: =B67 -> -1714.5 | C69: =B69+C67 -> -31415.145 | D69: =C69+D67 -> -40280.486 | E69: =D69+E67 -> -11338.977 | F69: =E69+F67 -> 13192.928 | G69: =F69+G67 -> 63935.762
A70: Recupero simple: a + b/c en el año del cruce | C70: =IF(AND(B68<0,C68>=0),C$3-1+(-B68)/C65,"") | D70: =IF(AND(C68<0,D68>=0),D$3-1+(-C68)/D65,"") | E70: =IF(AND(D68<0,E68>=0),E$3-1+(-D68)/E65,"") -> 2.9321736 | F70: =IF(AND(E68<0,F68>=0),F$3-1+(-E68)/F65,"") | G70: =IF(AND(F68<0,G68>=0),G$3-1+(-F68)/G65,"")
A71: Recupero descontado: a + b/c en el año del cruce | C71: =IF(AND(B69<0,C69>=0),C$3-1+(-B69)/C67,"") | D71: =IF(AND(C69<0,D69>=0),D$3-1+(-C69)/D67,"") | E71: =IF(AND(D69<0,E69>=0),E$3-1+(-D69)/E67,"") | F71: =IF(AND(E69<0,F69>=0),F$3-1+(-E69)/F67,"") -> 3.4622135 | G71: =IF(AND(F69<0,G69>=0),G$3-1+(-F69)/G67,"")
A73: Indicadores
A74: VAN (USD) | B74: =SUM(B67:G67) -> 63935.762
A75: TIR | B75: =IFERROR(IRR(B65:G65),"no definida") -> 0.72550446
A76: Payback simple (años) | B76: =IF(COUNT(C70:G70)=0,"no se recupera",MIN(C70:G70)) -> 2.9321736
A77: Payback descontado (años) | B77: =IF(COUNT(C71:G71)=0,"no se recupera",MIN(C71:G71)) -> 3.4622135
A78: VAN con valor residual (USD) | B78: =SUM(B67:G67)+MAX(0,G65-G62)*(1+crecimiento_perpetuo)/(tasa_descuento-crecimiento_perpetuo)/(1+tasa_descuento)^5 -> 199501.17
A79: Ingreso medio por cliente B2B en el año 5 (USD) | B79: =IFERROR(G45/G36,"no definido") -> 8901.2048
A80: Punto de equilibrio (clientes B2B) | B80: =IFERROR(ROUNDUP(G54/B79,0),"no definido") -> 23

Sheet Pesimista
A1: Escenario pesimista (USD nominales; todo lo derivado es fórmula)
A2: Columna de escenario en Supuestos (1 = optimista, 2 = neutral, 3 = pesimista) | B2: 3
A3: Año | B3: =COLUMN()-2 -> 0 | C3: =COLUMN()-2 -> 1 | D3: =COLUMN()-2 -> 2 | E3: =COLUMN()-2 -> 3 | F3: =COLUMN()-2 -> 4 | G3: =COLUMN()-2 -> 5
A4: Año calendario | B4: =anio_0+B$3 -> 2026 | C4: =anio_0+C$3 -> 2027 | D4: =anio_0+D$3 -> 2028 | E4: =anio_0+E$3 -> 2029 | F4: =anio_0+F$3 -> 2030 | G4: =anio_0+G$3 -> 2031
A5: Año electoral (1 = sí) | B5: =INDEX(anio_electoral,B$3+1) -> 0 | C5: =INDEX(anio_electoral,C$3+1) -> 1 | D5: =INDEX(anio_electoral,D$3+1) -> 0 | E5: =INDEX(anio_electoral,E$3+1) -> 1 | F5: =INDEX(anio_electoral,F$3+1) -> 0 | G5: =INDEX(anio_electoral,G$3+1) -> 1
A6: Usuarios activos mensuales | C6: =INDEX(usuarios_activos,C$3,$B$2) -> 500 | D6: =INDEX(usuarios_activos,D$3,$B$2) -> 2000 | E6: =INDEX(usuarios_activos,E$3,$B$2) -> 5000 | F6: =INDEX(usuarios_activos,F$3,$B$2) -> 8000 | G6: =INDEX(usuarios_activos,G$3,$B$2) -> 10000
A7: Ventas B2B habilitadas (1 = sí) | C7: =IF(C6>=ua_inicio_b2b,1,0) -> 0 | D7: =IF(D6>=ua_inicio_b2b,1,0) -> 0 | E7: =IF(E6>=ua_inicio_b2b,1,0) -> 1 | F7: =IF(F6>=ua_inicio_b2b,1,0) -> 1 | G7: =IF(G6>=ua_inicio_b2b,1,0) -> 1
A9: Clientes B2B
A10: Medios de gran porte: activos al inicio | C10: =N(B13) -> 0 | D10: =N(C13) -> 0 | E10: =N(D13) -> 0 | F10: =N(E13) -> 1 | G10: =N(F13) -> 1
A11: Medios de gran porte: bajas | C11: =ROUND(INDEX(churn_medios_grandes,1,$B$2)*C10,0) -> 0 | D11: =ROUND(INDEX(churn_medios_grandes,1,$B$2)*D10,0) -> 0 | E11: =ROUND(INDEX(churn_medios_grandes,1,$B$2)*E10,0) -> 0 | F11: =ROUND(INDEX(churn_medios_grandes,1,$B$2)*F10,0) -> 0 | G11: =ROUND(INDEX(churn_medios_grandes,1,$B$2)*G10,0) -> 0
A12: Medios de gran porte: altas | C12: =C7*ROUND(INDEX(capt_medios_grandes,1,$B$2)*sens_captacion*(u_medios_grandes-C10),0) -> 0 | D12: =D7*ROUND(INDEX(capt_medios_grandes,1,$B$2)*sens_captacion*(u_medios_grandes-D10),0) -> 0 | E12: =E7*ROUND(INDEX(capt_medios_grandes,1,$B$2)*sens_captacion*(u_medios_grandes-E10),0) -> 1 | F12: =F7*ROUND(INDEX(capt_medios_grandes,1,$B$2)*sens_captacion*(u_medios_grandes-F10),0) -> 0 | G12: =G7*ROUND(INDEX(capt_medios_grandes,1,$B$2)*sens_captacion*(u_medios_grandes-G10),0) -> 0
A13: Medios de gran porte: activos al cierre | C13: =C10+C12-C11 -> 0 | D13: =D10+D12-D11 -> 0 | E13: =E10+E12-E11 -> 1 | F13: =F10+F12-F11 -> 1 | G13: =G10+G12-G11 -> 1
A14: Medios de gran porte: promedio del año | C14: =(C10+C13)/2 -> 0 | D14: =(D10+D13)/2 -> 0 | E14: =(E10+E13)/2 -> 0.5 | F14: =(F10+F13)/2 -> 1 | G14: =(G10+G13)/2 -> 1
A15: Medios socios de ADEPA (resto): activos al inicio | C15: =N(B18) -> 0 | D15: =N(C18) -> 0 | E15: =N(D18) -> 0 | F15: =N(E18) -> 2 | G15: =N(F18) -> 3
A16: Medios socios de ADEPA (resto): bajas | C16: =ROUND(INDEX(churn_medios_chicos,1,$B$2)*C15,0) -> 0 | D16: =ROUND(INDEX(churn_medios_chicos,1,$B$2)*D15,0) -> 0 | E16: =ROUND(INDEX(churn_medios_chicos,1,$B$2)*E15,0) -> 0 | F16: =ROUND(INDEX(churn_medios_chicos,1,$B$2)*F15,0) -> 1 | G16: =ROUND(INDEX(churn_medios_chicos,1,$B$2)*G15,0) -> 1
A17: Medios socios de ADEPA (resto): altas | C17: =C7*ROUND(INDEX(capt_medios_chicos,1,$B$2)*sens_captacion*(u_medios_chicos-C15),0) -> 0 | D17: =D7*ROUND(INDEX(capt_medios_chicos,1,$B$2)*sens_captacion*(u_medios_chicos-D15),0) -> 0 | E17: =E7*ROUND(INDEX(capt_medios_chicos,1,$B$2)*sens_captacion*(u_medios_chicos-E15),0) -> 2 | F17: =F7*ROUND(INDEX(capt_medios_chicos,1,$B$2)*sens_captacion*(u_medios_chicos-F15),0) -> 2 | G17: =G7*ROUND(INDEX(capt_medios_chicos,1,$B$2)*sens_captacion*(u_medios_chicos-G15),0) -> 2
A18: Medios socios de ADEPA (resto): activos al cierre | C18: =C15+C17-C16 -> 0 | D18: =D15+D17-D16 -> 0 | E18: =E15+E17-E16 -> 2 | F18: =F15+F17-F16 -> 3 | G18: =G15+G17-G16 -> 4
A19: Medios socios de ADEPA (resto): promedio del año | C19: =(C15+C18)/2 -> 0 | D19: =(D15+D18)/2 -> 0 | E19: =(E15+E18)/2 -> 1 | F19: =(F15+F18)/2 -> 2.5 | G19: =(G15+G18)/2 -> 3.5
A20: Verificadores: activos al inicio | C20: =N(B23) -> 0 | D20: =N(C23) -> 0 | E20: =N(D23) -> 0 | F20: =N(E23) -> 1 | G20: =N(F23) -> 1
A21: Verificadores: bajas | C21: =ROUND(INDEX(churn_verificadores,1,$B$2)*C20,0) -> 0 | D21: =ROUND(INDEX(churn_verificadores,1,$B$2)*D20,0) -> 0 | E21: =ROUND(INDEX(churn_verificadores,1,$B$2)*E20,0) -> 0 | F21: =ROUND(INDEX(churn_verificadores,1,$B$2)*F20,0) -> 0 | G21: =ROUND(INDEX(churn_verificadores,1,$B$2)*G20,0) -> 0
A22: Verificadores: altas | C22: =C7*ROUND(INDEX(capt_verificadores,1,$B$2)*sens_captacion*(u_verificadores-C20),0) -> 0 | D22: =D7*ROUND(INDEX(capt_verificadores,1,$B$2)*sens_captacion*(u_verificadores-D20),0) -> 0 | E22: =E7*ROUND(INDEX(capt_verificadores,1,$B$2)*sens_captacion*(u_verificadores-E20),0) -> 1 | F22: =F7*ROUND(INDEX(capt_verificadores,1,$B$2)*sens_captacion*(u_verificadores-F20),0) -> 0 | G22: =G7*ROUND(INDEX(capt_verificadores,1,$B$2)*sens_captacion*(u_verificadores-G20),0) -> 0
A23: Verificadores: activos al cierre | C23: =C20+C22-C21 -> 0 | D23: =D20+D22-D21 -> 0 | E23: =E20+E22-E21 -> 1 | F23: =F20+F22-F21 -> 1 | G23: =G20+G22-G21 -> 1
A24: Verificadores: promedio del año | C24: =(C20+C23)/2 -> 0 | D24: =(D20+D23)/2 -> 0 | E24: =(E20+E23)/2 -> 0.5 | F24: =(F20+F23)/2 -> 1 | G24: =(G20+G23)/2 -> 1
A25: Universidades y observatorios: activos al inicio | C25: =N(B28) -> 0 | D25: =N(C28) -> 0 | E25: =N(D28) -> 0 | F25: =N(E28) -> 3 | G25: =N(F28) -> 6
A26: Universidades y observatorios: bajas | C26: =ROUND(INDEX(churn_universidades,1,$B$2)*C25,0) -> 0 | D26: =ROUND(INDEX(churn_universidades,1,$B$2)*D25,0) -> 0 | E26: =ROUND(INDEX(churn_universidades,1,$B$2)*E25,0) -> 0 | F26: =ROUND(INDEX(churn_universidades,1,$B$2)*F25,0) -> 0 | G26: =ROUND(INDEX(churn_universidades,1,$B$2)*G25,0) -> 1
A27: Universidades y observatorios: altas | C27: =C7*ROUND(INDEX(capt_universidades,1,$B$2)*sens_captacion*(u_universidades-C25),0) -> 0 | D27: =D7*ROUND(INDEX(capt_universidades,1,$B$2)*sens_captacion*(u_universidades-D25),0) -> 0 | E27: =E7*ROUND(INDEX(capt_universidades,1,$B$2)*sens_captacion*(u_universidades-E25),0) -> 3 | F27: =F7*ROUND(INDEX(capt_universidades,1,$B$2)*sens_captacion*(u_universidades-F25),0) -> 3 | G27: =G7*ROUND(INDEX(capt_universidades,1,$B$2)*sens_captacion*(u_universidades-G25),0) -> 3
A28: Universidades y observatorios: activos al cierre | C28: =C25+C27-C26 -> 0 | D28: =D25+D27-D26 -> 0 | E28: =E25+E27-E26 -> 3 | F28: =F25+F27-F26 -> 6 | G28: =G25+G27-G26 -> 8
A29: Universidades y observatorios: promedio del año | C29: =(C25+C28)/2 -> 0 | D29: =(D25+D28)/2 -> 0 | E29: =(E25+E28)/2 -> 1.5 | F29: =(F25+F28)/2 -> 4.5 | G29: =(G25+G28)/2 -> 7
A30: Agencias: activos al inicio | C30: =N(B33) -> 0 | D30: =N(C33) -> 0 | E30: =N(D33) -> 0 | F30: =N(E33) -> 1 | G30: =N(F33) -> 2
A31: Agencias: bajas | C31: =ROUND(INDEX(churn_agencias,1,$B$2)*C30,0) -> 0 | D31: =ROUND(INDEX(churn_agencias,1,$B$2)*D30,0) -> 0 | E31: =ROUND(INDEX(churn_agencias,1,$B$2)*E30,0) -> 0 | F31: =ROUND(INDEX(churn_agencias,1,$B$2)*F30,0) -> 0 | G31: =ROUND(INDEX(churn_agencias,1,$B$2)*G30,0) -> 1
A32: Agencias: altas | C32: =C7*ROUND(INDEX(capt_agencias,1,$B$2)*sens_captacion*(u_agencias-C30),0) -> 0 | D32: =D7*ROUND(INDEX(capt_agencias,1,$B$2)*sens_captacion*(u_agencias-D30),0) -> 0 | E32: =E7*ROUND(INDEX(capt_agencias,1,$B$2)*sens_captacion*(u_agencias-E30),0) -> 1 | F32: =F7*ROUND(INDEX(capt_agencias,1,$B$2)*sens_captacion*(u_agencias-F30),0) -> 1 | G32: =G7*ROUND(INDEX(capt_agencias,1,$B$2)*sens_captacion*(u_agencias-G30),0) -> 1
A33: Agencias: activos al cierre | C33: =C30+C32-C31 -> 0 | D33: =D30+D32-D31 -> 0 | E33: =E30+E32-E31 -> 1 | F33: =F30+F32-F31 -> 2 | G33: =G30+G32-G31 -> 2
A34: Agencias: promedio del año | C34: =(C30+C33)/2 -> 0 | D34: =(D30+D33)/2 -> 0 | E34: =(E30+E33)/2 -> 0.5 | F34: =(F30+F33)/2 -> 1.5 | G34: =(G30+G33)/2 -> 2
A35: Organismos y ONG: contratos | C35: =C5*C7*ROUND(INDEX(capt_organismos,1,$B$2)*sens_captacion*u_organismos,0) -> 0 | D35: =D5*D7*ROUND(INDEX(capt_organismos,1,$B$2)*sens_captacion*u_organismos,0) -> 0 | E35: =E5*E7*ROUND(INDEX(capt_organismos,1,$B$2)*sens_captacion*u_organismos,0) -> 1 | F35: =F5*F7*ROUND(INDEX(capt_organismos,1,$B$2)*sens_captacion*u_organismos,0) -> 0 | G35: =G5*G7*ROUND(INDEX(capt_organismos,1,$B$2)*sens_captacion*u_organismos,0) -> 1
A36: Clientes B2B (promedio del año, con contratos) | C36: =C14+C19+C24+C29+C34+C35 -> 0 | D36: =D14+D19+D24+D29+D34+D35 -> 0 | E36: =E14+E19+E24+E29+E34+E35 -> 5 | F36: =F14+F19+F24+F29+F34+F35 -> 10.5 | G36: =G14+G19+G24+G29+G34+G35 -> 15.5
A38: Ingresos por producto
A39: Ingresos: API nivel superior (Medios de gran porte) | C39: =C14*INDEX(precio_medios_grandes,1,$B$2)*sens_precios*meses_anio -> 0 | D39: =D14*INDEX(precio_medios_grandes,1,$B$2)*sens_precios*meses_anio -> 0 | E39: =E14*INDEX(precio_medios_grandes,1,$B$2)*sens_precios*meses_anio -> 9000 | F39: =F14*INDEX(precio_medios_grandes,1,$B$2)*sens_precios*meses_anio -> 18000 | G39: =G14*INDEX(precio_medios_grandes,1,$B$2)*sens_precios*meses_anio -> 18000
A40: Ingresos: API nivel intermedio (Medios socios de ADEPA (resto)) | C40: =C19*precio_medios_chicos*sens_precios*meses_anio -> 0 | D40: =D19*precio_medios_chicos*sens_precios*meses_anio -> 0 | E40: =E19*precio_medios_chicos*sens_precios*meses_anio -> 2400 | F40: =F19*precio_medios_chicos*sens_precios*meses_anio -> 6000 | G40: =G19*precio_medios_chicos*sens_precios*meses_anio -> 8400
A41: Ingresos: panel de tendencias y API intermedia (Verificadores) | C41: =C24*precio_verificadores*sens_precios*meses_anio -> 0 | D41: =D24*precio_verificadores*sens_precios*meses_anio -> 0 | E41: =E24*precio_verificadores*sens_precios*meses_anio -> 3000 | F41: =F24*precio_verificadores*sens_precios*meses_anio -> 6000 | G41: =G24*precio_verificadores*sens_precios*meses_anio -> 6000
A42: Ingresos: acceso histórico (Universidades y observatorios) | C42: =C29*precio_universidades*sens_precios*meses_anio -> 0 | D42: =D29*precio_universidades*sens_precios*meses_anio -> 0 | E42: =E29*precio_universidades*sens_precios*meses_anio -> 1800 | F42: =F29*precio_universidades*sens_precios*meses_anio -> 5400 | G42: =G29*precio_universidades*sens_precios*meses_anio -> 8400
A43: Ingresos: API nivel superior (Agencias) | C43: =C34*INDEX(precio_agencias,1,$B$2)*sens_precios*meses_anio -> 0 | D43: =D34*INDEX(precio_agencias,1,$B$2)*sens_precios*meses_anio -> 0 | E43: =E34*INDEX(precio_agencias,1,$B$2)*sens_precios*meses_anio -> 9000 | F43: =F34*INDEX(precio_agencias,1,$B$2)*sens_precios*meses_anio -> 27000 | G43: =G34*INDEX(precio_agencias,1,$B$2)*sens_precios*meses_anio -> 36000
A44: Ingresos: reportes de monitoreo electoral, organismos y ONG | C44: =C35*INDEX(precio_organismos,1,$B$2)*sens_precios -> 0 | D44: =D35*INDEX(precio_organismos,1,$B$2)*sens_precios -> 0 | E44: =E35*INDEX(precio_organismos,1,$B$2)*sens_precios -> 10000 | F44: =F35*INDEX(precio_organismos,1,$B$2)*sens_precios -> 0 | G44: =G35*INDEX(precio_organismos,1,$B$2)*sens_precios -> 10000
A45: Ingresos totales | B45: =SUM(B39:B44) -> 0 | C45: =SUM(C39:C44) -> 0 | D45: =SUM(D39:D44) -> 0 | E45: =SUM(E39:E44) -> 35200 | F45: =SUM(F39:F44) -> 62400 | G45: =SUM(G39:G44) -> 86800
A47: Costos por rubro
A48: Costo: recursos humanos (desarrollador semi senior, con cargas sociales) | C48: =sueldo_usd*sueldos_por_anio*(1+cargas_sociales)*(1+ajuste_sueldo)^C$3 -> 30786.21 | D48: =sueldo_usd*sueldos_por_anio*(1+cargas_sociales)*(1+ajuste_sueldo)^D$3 -> 32325.52 | E48: =sueldo_usd*sueldos_por_anio*(1+cargas_sociales)*(1+ajuste_sueldo)^E$3 -> 33941.797 | F48: =sueldo_usd*sueldos_por_anio*(1+cargas_sociales)*(1+ajuste_sueldo)^F$3 -> 35638.886 | G48: =sueldo_usd*sueldos_por_anio*(1+cargas_sociales)*(1+ajuste_sueldo)^G$3 -> 37420.831
A49: Costo: infraestructura | B49: =inv_infraestructura_0 -> 156 | C49: =meses_anio*(infra_base+infra_escalado*C6/ua_escalado)+dominio_anual -> 251.5 | D49: =meses_anio*(infra_base+infra_escalado*D6/ua_escalado)+dominio_anual -> 269.5 | E49: =meses_anio*(infra_base+infra_escalado*E6/ua_escalado)+dominio_anual -> 305.5 | F49: =meses_anio*(infra_base+infra_escalado*F6/ua_escalado)+dominio_anual -> 341.5 | G49: =meses_anio*(infra_base+infra_escalado*G6/ua_escalado)+dominio_anual -> 365.5
A50: Costo: marketing | C50: =INDEX(marketing,C$3,$B$2) -> 2000 | D50: =INDEX(marketing,D$3,$B$2) -> 3000 | E50: =INDEX(marketing,E$3,$B$2) -> 4000 | F50: =INDEX(marketing,F$3,$B$2) -> 5000 | G50: =INDEX(marketing,G$3,$B$2) -> 6000
A51: Costo: dominio, marca y asesoría legal | B51: =inv_dominio+inv_marca_inpi+inv_legal -> 1558.5
A52: Costo variable: análisis de usuarios gratuitos | C52: =C6*MIN(INDEX(analisis_por_ua_mes,1,$B$2),tope_mensual)*meses_anio*(1-INDEX(tasa_reuso,1,$B$2))*INDEX(costo_analisis,1,$B$2)*sens_costo_analisis -> 911.136 | D52: =D6*MIN(INDEX(analisis_por_ua_mes,1,$B$2),tope_mensual)*meses_anio*(1-INDEX(tasa_reuso,1,$B$2))*INDEX(costo_analisis,1,$B$2)*sens_costo_analisis -> 3644.544 | E52: =E6*MIN(INDEX(analisis_por_ua_mes,1,$B$2),tope_mensual)*meses_anio*(1-INDEX(tasa_reuso,1,$B$2))*INDEX(costo_analisis,1,$B$2)*sens_costo_analisis -> 9111.36 | F52: =F6*MIN(INDEX(analisis_por_ua_mes,1,$B$2),tope_mensual)*meses_anio*(1-INDEX(tasa_reuso,1,$B$2))*INDEX(costo_analisis,1,$B$2)*sens_costo_analisis -> 14578.176 | G52: =G6*MIN(INDEX(analisis_por_ua_mes,1,$B$2),tope_mensual)*meses_anio*(1-INDEX(tasa_reuso,1,$B$2))*INDEX(costo_analisis,1,$B$2)*sens_costo_analisis -> 18222.72
A53: Costo variable: consultas de la API B2B | C53: =((C19+C24)*MIN(INDEX(consultas_pro_mes,1,$B$2),cuota_intermedia)+(C14+C34)*MIN(INDEX(consultas_ent_mes,1,$B$2),cuota_superior))*meses_anio*(1-INDEX(tasa_reuso,1,$B$2))*INDEX(costo_analisis,1,$B$2)*sens_costo_analisis -> 0 | D53: =((D19+D24)*MIN(INDEX(consultas_pro_mes,1,$B$2),cuota_intermedia)+(D14+D34)*MIN(INDEX(consultas_ent_mes,1,$B$2),cuota_superior))*meses_anio*(1-INDEX(tasa_reuso,1,$B$2))*INDEX(costo_analisis,1,$B$2)*sens_costo_analisis -> 0 | E53: =((E19+E24)*MIN(INDEX(consultas_pro_mes,1,$B$2),cuota_intermedia)+(E14+E34)*MIN(INDEX(consultas_ent_mes,1,$B$2),cuota_superior))*meses_anio*(1-INDEX(tasa_reuso,1,$B$2))*INDEX(costo_analisis,1,$B$2)*sens_costo_analisis -> 17311.584 | F53: =((F19+F24)*MIN(INDEX(consultas_pro_mes,1,$B$2),cuota_intermedia)+(F14+F34)*MIN(INDEX(consultas_ent_mes,1,$B$2),cuota_superior))*meses_anio*(1-INDEX(tasa_reuso,1,$B$2))*INDEX(costo_analisis,1,$B$2)*sens_costo_analisis -> 42823.392 | G53: =((G19+G24)*MIN(INDEX(consultas_pro_mes,1,$B$2),cuota_intermedia)+(G14+G34)*MIN(INDEX(consultas_ent_mes,1,$B$2),cuota_superior))*meses_anio*(1-INDEX(tasa_reuso,1,$B$2))*INDEX(costo_analisis,1,$B$2)*sens_costo_analisis -> 51934.752
A54: Costos totales | B54: =SUM(B48:B53) -> 1714.5 | C54: =SUM(C48:C53) -> 33948.846 | D54: =SUM(D48:D53) -> 39239.565 | E54: =SUM(E48:E53) -> 64670.241 | F54: =SUM(F48:F53) -> 98381.954 | G54: =SUM(G48:G53) -> 113943.8
A56: Impuesto y capital de trabajo
A57: Resultado antes de impuestos | B57: =B45-B54 -> -1714.5 | C57: =C45-C54 -> -33948.846 | D57: =D45-D54 -> -39239.565 | E57: =E45-E54 -> -29470.241 | F57: =F45-F54 -> -35981.954 | G57: =G45-G54 -> -27143.803
A58: Quebranto acumulado | B58: =MIN(0,B57) -> -1714.5 | C58: =MIN(0,B58+C57) -> -35663.346 | D58: =MIN(0,C58+D57) -> -74902.91 | E58: =MIN(0,D58+E57) -> -104373.15 | F58: =MIN(0,E58+F57) -> -140355.11 | G58: =MIN(0,F58+G57) -> -167498.91
A59: Impuesto a las ganancias | B59: =alicuota_ganancias*MAX(0,B57) -> 0 | C59: =alicuota_ganancias*MAX(0,B58+C57) -> 0 | D59: =alicuota_ganancias*MAX(0,C58+D57) -> 0 | E59: =alicuota_ganancias*MAX(0,D58+E57) -> 0 | F59: =alicuota_ganancias*MAX(0,E58+F57) -> 0 | G59: =alicuota_ganancias*MAX(0,F58+G57) -> 0
A60: Capital de trabajo | B60: =meses_cobro/meses_anio*B45 -> 0 | C60: =meses_cobro/meses_anio*C45 -> 0 | D60: =meses_cobro/meses_anio*D45 -> 0 | E60: =meses_cobro/meses_anio*E45 -> 5866.6667 | F60: =meses_cobro/meses_anio*F45 -> 10400 | G60: =meses_cobro/meses_anio*G45 -> 14466.667
A61: Capital de trabajo: variación | B61: =B60 -> 0 | C61: =C60-B60 -> 0 | D61: =D60-C60 -> 0 | E61: =E60-D60 -> 5866.6667 | F61: =F60-E60 -> 4533.3333 | G61: =G60-F60 -> 4066.6667
A62: Recupero del capital de trabajo | G62: =G60 -> 14466.667
A64: Flujo de caja
A65: Flujo neto | B65: =B57-B59-B61+N(B62) -> -1714.5 | C65: =C57-C59-C61+N(C62) -> -33948.846 | D65: =D57-D59-D61+N(D62) -> -39239.565 | E65: =E57-E59-E61+N(E62) -> -35336.907 | F65: =F57-F59-F61+N(F62) -> -40515.288 | G65: =G57-G59-G61+N(G62) -> -16743.803
A66: Factor de descuento | B66: =1/(1+tasa_descuento)^B$3 -> 1 | C66: =1/(1+tasa_descuento)^C$3 -> 0.8 | D66: =1/(1+tasa_descuento)^D$3 -> 0.64 | E66: =1/(1+tasa_descuento)^E$3 -> 0.512 | F66: =1/(1+tasa_descuento)^F$3 -> 0.4096 | G66: =1/(1+tasa_descuento)^G$3 -> 0.32768
A67: Flujo descontado | B67: =B65*B66 -> -1714.5 | C67: =C65*C66 -> -27159.077 | D67: =D65*D66 -> -25113.321 | E67: =E65*E66 -> -18092.496 | F67: =F65*F66 -> -16595.062 | G67: =G65*G66 -> -5486.6093
A68: Flujo neto acumulado | B68: =B65 -> -1714.5 | C68: =B68+C65 -> -35663.346 | D68: =C68+D65 -> -74902.91 | E68: =D68+E65 -> -110239.82 | F68: =E68+F65 -> -150755.11 | G68: =F68+G65 -> -167498.91
A69: Flujo descontado acumulado | B69: =B67 -> -1714.5 | C69: =B69+C67 -> -28873.577 | D69: =C69+D67 -> -53986.898 | E69: =D69+E67 -> -72079.395 | F69: =E69+F67 -> -88674.456 | G69: =F69+G67 -> -94161.066
A70: Recupero simple: a + b/c en el año del cruce | C70: =IF(AND(B68<0,C68>=0),C$3-1+(-B68)/C65,"") | D70: =IF(AND(C68<0,D68>=0),D$3-1+(-C68)/D65,"") | E70: =IF(AND(D68<0,E68>=0),E$3-1+(-D68)/E65,"") | F70: =IF(AND(E68<0,F68>=0),F$3-1+(-E68)/F65,"") | G70: =IF(AND(F68<0,G68>=0),G$3-1+(-F68)/G65,"")
A71: Recupero descontado: a + b/c en el año del cruce | C71: =IF(AND(B69<0,C69>=0),C$3-1+(-B69)/C67,"") | D71: =IF(AND(C69<0,D69>=0),D$3-1+(-C69)/D67,"") | E71: =IF(AND(D69<0,E69>=0),E$3-1+(-D69)/E67,"") | F71: =IF(AND(E69<0,F69>=0),F$3-1+(-E69)/F67,"") | G71: =IF(AND(F69<0,G69>=0),G$3-1+(-F69)/G67,"")
A73: Indicadores
A74: VAN (USD) | B74: =SUM(B67:G67) -> -94161.066
A75: TIR | B75: =IFERROR(IRR(B65:G65),"no definida") -> no definida
A76: Payback simple (años) | B76: =IF(COUNT(C70:G70)=0,"no se recupera",MIN(C70:G70)) -> no se recupera
A77: Payback descontado (años) | B77: =IF(COUNT(C71:G71)=0,"no se recupera",MIN(C71:G71)) -> no se recupera
A78: VAN con valor residual (USD) | B78: =SUM(B67:G67)+MAX(0,G65-G62)*(1+crecimiento_perpetuo)/(tasa_descuento-crecimiento_perpetuo)/(1+tasa_descuento)^5 -> -94161.066
A79: Ingreso medio por cliente B2B en el año 5 (USD) | B79: =IFERROR(G45/G36,"no definido") -> 5600
A80: Punto de equilibrio (clientes B2B) | B80: =IFERROR(ROUNDUP(G54/B79,0),"no definido") -> 21
